Workbook

Sheet ASVS Results
A1: Security Category | B1: Valid criteria | C1: Total criteria | D1: Validity Percentage | E1: ASVS Level Acquired
A2: Architecture, Design and Threat Modeling | B2: =0+COUNTIF('Architecture, Design and Threat'!G2:G45,"Valid") -> 26 | C2: =COUNTIF('Architecture, Design and Threat'!G2:G45,"<>Not Applicable") -> 29 | D2: =(B2/C2)*100 -> 89.655172
A3: Authentication | B3: =COUNTIF(Authentication!G2:G58,"Valid") -> 16 | C3: =COUNTIF(Authentication!G2:G58,"<>Not Applicable") -> 16 | D3: =(B3/C3)*100 -> 100
A4: Session Management | B4: =COUNTIF('Session Management'!G2:G21,"Valid") -> 8 | C4: =COUNTIF('Session Management'!G2:G21,"<>Not Applicable") -> 8 | D4: =(B4/C4)*100 -> 100
A5: Access Control | B5: =COUNTIF('Access Control'!G2:G11,"Valid") -> 5 | C5: =COUNTIF('Access Control'!G2:G11,"<>Not Applicable") -> 5 | D5: =(B5/C5)*100 -> 100
A6: Validation, Sanitization and Encoding | B6: =COUNTIF('Validation, Sanitization and En'!G2:G31,"Valid") -> 16 | C6: =COUNTIF('Validation, Sanitization and En'!G2:G31,"<>Not Applicable") -> 16 | D6: =(B6/C6)*100 -> 100
A7: Stored Cryptography | B7: =COUNTIF('Stored Cryptography'!G2:G17,"Valid") -> 12 | C7: =COUNTIF('Stored Cryptography'!G2:G17,"<>Not Applicable") -> 13 | D7: =(B7/C7)*100 -> 92.307692
A8: Error Handling and Logging | B8: =COUNTIF('Error Handling and Logging'!G2:G14,"Valid") -> 10 | C8: =COUNTIF('Error Handling and Logging'!G2:G14,"<>Not Applicable") -> 10 | D8: =(B8/C8)*100 -> 100
A9: Data Protection | B9: =COUNTIF('Data Protection'!G2:G18,"Valid") -> 8 | C9: =COUNTIF('Data Protection'!G2:G18,"<>Not Applicable") -> 8 | D9: =(B9/C9)*100 -> 100
A10: Communication | B10: =COUNTIF(Communication!G2:G9,"Valid") -> 6 | C10: =COUNTIF(Communication!G2:G9,"<>Not Applicable") -> 6 | D10: =(B10/C10)*100 -> 100
A11: Malicious Code | B11: =COUNTIF('Malicious Code'!G2:G11,"Valid") -> 4 | C11: =COUNTIF('Malicious Code'!G2:G11,"<>Not Applicable") -> 4 | D11: =(B11/C11)*100 -> 100
A12: Business Logic | B12: =COUNTIF('Business Logic'!G2:G9,"Valid") -> 6 | C12: =COUNTIF('Business Logic'!G2:G9,"<>Not Applicable") -> 6 | D12: =(B12/C12)*100 -> 100
A13: Files and Resources | B13: =COUNTIF('Files and Resources'!G2:G16,"Valid") -> 5 | C13: =COUNTIF('Files and Resources'!G2:G16,"<>Not Applicable") -> 5 | D13: =(B13/C13)*100 -> 100
A14: API and Web Service | B14: =COUNTIF('API and Web Service'!G2:G16,"Valid") -> 7 | C14: =COUNTIF('API and Web Service'!G2:G16,"<>Not Applicable") -> 7 | D14: =(B14/C14)*100 -> 100
A15: Configuration | B15: =COUNTIF(Configuration!G2:G26,"Valid") -> 16 | C15: =COUNTIF(Configuration!G2:G26,"<>Not Applicable") -> 16 | D15: =(B15/C15)*100 -> 100
A16: Total | B16: =SUM(B2:B15) -> 145 | C16: =SUM(C2:C15) -> 149 | D16: =(B16/C16)*100 -> 97.315436

Sheet Architecture, Design and Threat
A1: Area | B1: # | C1: ASVS Level | D1: CWE | E1: NIST | F1: Verification Requirement | G1: Valid | H1: Source Code Reference | I1: Comment | J1: Tool Used
A2: Secure Software Development Lifecycle | B2: 1.1.1 | C2: 2 | F2: Verify the use of a secure software development lifecycle that addresses security in all stages of development. ([C1](https://owasp.org/www-project-proactive-controls/#div-numbering)) | G2: Valid | H2: https://github.com/IsepMartimOliveira/desofs2025_wed_ffs_4/blob/main/src/main/java/com/example/psoft_22_23_project/devicemanagement/model/MacAddress.java | I2: The architecture is designed with security in mind: the database is hosted on the same machine as the API to limit external access and reduce the attack surface. The system uses JWT (JSON Web Tokens) for authentication, and implements strong input validation measures, such as enforcing a strict regex pattern for MAC address validation. Additionally, the chosen architecture is flexible and supports future maintenance and security enhancements, making it easier to implement new validation mechanisms and strengthen overall system protection over time.
B3: 1.1.2 | C3: 2 | D3: 1053 | F3: Verify the use of threat modeling for every design change or sprint planning to identify threats, plan for countermeasures, facilitate appropriate risk responses, and guide security testing. | G3: Valid | H3: https://github.com/IsepMartimOliveira/desofs2025_wed_ffs_4/blob/docs/phase1/Deliverables/Phase1/ssdlc/ThreatModeling.md https://github.com/IsepMartimOliveira/desofs2025_wed_ffs_4/blob/docs/phase1/Deliverables/Phase1/ssdlc/Abuse_Case.md | I3: Threat Modeling and Abuse Cases documents
B4: 1.1.3 | C4: 2 | D4: 1110 | F4: Verify that all user stories and features contain functional security constraints, such as "As a user, I should be able to view and edit my profile. I should not be able to view or edit anyone else's profile" | G4: Valid | H4: https://github.com/IsepMartimOliveira/desofs2025_wed_ffs_4/blob/docs/phase1/Deliverables/Phase1/docs/ArchithectureAnalysis.md | I4: Security Requirements section
B5: 1.1.4 | C5: 2 | D5: 1059 | F5: Verify documentation and justification of all the application's trust boundaries, components, and significant data flows. | G5: Valid | H5: https://github.com/IsepMartimOliveira/desofs2025_wed_ffs_4/blob/docs/phase1/Deliverables/Phase1/ssdlc/ThreatModeling.md | I5: Threat Modeling
B6: 1.1.5 | C6: 2 | D6: 1059 | F6: Verify definition and security analysis of the application's high-level architecture and all connected remote services. ([C1](https://owasp.org/www-project-proactive-controls/#div-numbering)) | G6: Valid | H6: https://github.com/IsepMartimOliveira/desofs2025_wed_ffs_4/blob/docs/phase1/Deliverables/Phase1/docs/ArchithectureAnalysis.md | I6: Deployment View
B7: 1.1.6 | C7: 2 | D7: 637 | F7: Verify implementation of centralized, simple (economy of design), vetted, secure, and reusable security controls to avoid duplicate, missing, ineffective, or insecure controls. ([C10](https://owasp.org/www-project-proactive-controls/#div-numbering)) | G7: Valid | H7: https://github.com/IsepMartimOliveira/desofs2025_wed_ffs_4/blob/main/src/main/java/com/example/psoft_22_23_project/configuration/SecurityConfig.java | I7: Between lines 93–229 centralizes authentication, authorization, session management, password encoding, and CORS settings
B8: 1.1.7 | C8: 2 | D8: 637 | F8: Verify availability of a secure coding checklist, security requirements, guideline, or policy to all developers and testers. | G8: Valid | H8: https://github.com/IsepMartimOliveira/desofs2025_wed_ffs_4/tree/docs/phase1/Deliverables/Phase1/v4-ASVS-checklist-en.xlsx https://github.com/IsepMartimOliveira/desofs2025_wed_ffs_4/blob/docs/phase1/Deliverables/Phase1/docs/ArchithectureAnalysis.md | I8: ASVS Checklist and Archithecture Analysis
A9: Authentication Architecture | B9: 1.2.1 | C9: 2 | D9: 250 | F9: Verify the use of unique or special low-privilege operating system accounts for all application components, services, and servers. ([C3](https://owasp.org/www-project-proactive-controls/#div-numbering)) | G9: Valid | H9: https://github.com/IsepMartimOliveira/desofs2025_wed_ffs_4/blob/main/src/main/java/com/example/psoft_22_23_project/configuration/SecurityConfig.java | I9: Between lines 121 and 166
B10: 1.2.2 | C10: 2 | D10: 306 | F10: Verify that communications between application components, including APIs, middleware and data layers, are authenticated. Components should have the least necessary privileges needed. ([C3](https://owasp.org/www-project-proactive-controls/#div-numbering)) | G10: Valid | H10: https://github.com/IsepMartimOliveira/desofs2025_wed_ffs_4/blob/docs/phase1/src/main/java/com/example/psoft_22_23_project/configuration/SecurityConfig.java | I10: Method in line 98
B11: 1.2.3 | C11: 2 | D11: 306 | F11: Verify that the application uses a single vetted authentication mechanism that is known to be secure, can be extended to include strong authentication, and has sufficient logging and monitoring to detect account abuse or breaches. | G11: Valid | H11: https://github.com/IsepMartimOliveira/desofs2025_wed_ffs_4/blob/docs/phase1/src/main/java/com/example/psoft_22_23_project/configuration/SecurityConfig.java | I11: Methods between line 98 and line 180
B12: 1.2.4 | C12: 2 | D12: 306 | F12: Verify that all authentication pathways and identity management APIs implement consistent authentication security control strength, such that there are no weaker alternatives per the risk of the application. | G12: Valid | H12: https://github.com/IsepMartimOliveira/desofs2025_wed_ffs_4/blob/docs/phase1/src/main/java/com/example/psoft_22_23_project/api/AuthApi.java | I12: login method, uses JWT Token with expirancy date
A13: Session Management Architecture | F13: This is a placeholder for future architectural requirements. | G13: Not Applicable
A14: Access Control Architecture | B14: 1.4.1 | C14: 2 | D14: 602 | F14: Verify that trusted enforcement points such as at access control gateways, servers, and serverless functions enforce access controls. Never enforce access controls on the client. | G14: Valid | H14: https://github.com/IsepMartimOliveira/desofs2025_wed_ffs_4/blob/docs/phase1/src/main/java/com/example/psoft_22_23_project/configuration/SecurityConfig.java | I14: Methods between line 172 to 195
B15: 1.4.2 | C15: 2 | D15: 284 | F15: [DELETED, NOT ACTIONABLE] | G15: Not Applicable
B16: 1.4.3 | C16: 2 | D16: 272 | F16: [DELETED, DUPLICATE OF 4.1.3] | G16: Not Applicable
B17: 1.4.4 | C17: 2 | D17: 284 | F17: Verify the application uses a single and well-vetted access control mechanism for accessing protected data and resources. All requests must pass through this single mechanism to avoid copy and paste or insecure alternative paths. ([C7](https://owasp.org/www-project-proactive-controls/#div-numbering)) | G17: Valid | H17: https://github.com/IsepMartimOliveira/desofs2025_wed_ffs_4/blob/docs/phase1/src/main/java/com/example/psoft_22_23_project/api/AuthApi.java | I17: Only point of acess is login endpoint, it authenthicates the jwt token
B18: 1.4.5 | C18: 2 | D18: 275 | F18: Verify that attribute or feature-based access control is used whereby the code checks the user's authorization for a feature/data item rather than just their role. Permissions should still be allocated using roles. ([C7](https://owasp.org/www-project-proactive-controls/#div-numbering)) | G18: Valid | H18: https://github.com/IsepMartimOliveira/desofs2025_wed_ffs_4/blob/main/src/main/java/com/example/psoft_22_23_project/subscriptionsmanagement/services/SubscriptionsServiceImpl.java | I18: Method ChangePlan
A19: Input and Output Architecture | B19: 1.5.1 | C19: 2 | D19: 1029 | F19: Verify that input and output requirements clearly define how to handle and process data based on type, content, and applicable laws, regulations, and other policy compliance. | G19: Valid | H19: https://github.com/IsepMartimOliveira/desofs2025_wed_ffs_4/blob/docs/phase1/src/main/java/com/example/psoft_22_23_project/devicemanagement/model/MacAddress.java | I19: Between line 16 to 18
B20: 1.5.2 | C20: 2 | D20: 502 | F20: Verify that serialization is not used when communicating with untrusted clients. If this is not possible, ensure that adequate integrity controls (and possibly encryption if sensitive data is sent) are enforced to prevent deserialization attacks including object injection. | G20: Not Applicable
B21: 1.5.3 | C21: 2 | D21: 602 | F21: Verify that input validation is enforced on a trusted service layer. ([C5](https://owasp.org/www-project-proactive-controls/#div-numbering)) | G21: Valid | H21: https://github.com/IsepMartimOliveira/desofs2025_wed_ffs_4/blob/docs/phase1/src/main/java/com/example/psoft_22_23_project/devicemanagement/services/DeviceServiceImpl.java | I21: In all the methods
B22: 1.5.4 | C22: 2 | D22: 116 | F22: Verify that output encoding occurs close to or by the interpreter for which it is intended. ([C4](https://www.owasp.org/index.php/OWASP_Proactive_Controls#tab=Formal_Numbering)) | G22: Not Applicable
A23: Cryptographic Architecture | B23: 1.6.1 | C23: 2 | D23: 320 | F23: Verify that there is an explicit policy for management of cryptographic keys and that a cryptographic key lifecycle follows a key management standard such as NIST SP 800-57. | G23: Valid | H23: https://github.com/IsepMartimOliveira/desofs2025_wed_ffs_4/blob/docs/phase1/src/main/java/com/example/psoft_22_23_project/configuration/SecurityConfig.java | I23: Between line 79 to 88
B24: 1.6.2 | C24: 2 | D24: 320 | F24: Verify that consumers of cryptographic services protect key material and other secrets by using key vaults or API based alternatives. | G24: Valid | H24: https://github.com/IsepMartimOliveira/desofs2025_wed_ffs_4/blob/docs/phase1/src/main/java/com/example/psoft_22_23_project/configuration/SecurityConfig.java | I24: Between line 79 to 88
B25: 1.6.3 | C25: 2 | D25: 320 | F25: Verify that all keys and passwords are replaceable and are part of a well-defined process to re-encrypt sensitive data. | G25: Non-valid
B26: 1.6.4 | C26: 2 | D26: 320 | F26: Verify that the architecture treats client-side secrets--such as symmetric keys, passwords, or API tokens--as insecure and never uses them to protect or access sensitive data. | G26: Not Applicable
A27: Error, Logging and Auditing Architecture | B27: 1.7.1 | C27: 2 | D27: 1009 | F27: Verify that a common logging format and approach is used across the system. ([C9](https://owasp.org/www-project-proactive-controls/#div-numbering)) | G27: Not Applicable
B28: 1.7.2 | C28: 2 | F28: Verify that logs are securely transmitted to a preferably remote system for analysis, detection, alerting, and escalation. ([C9](https://owasp.org/www-project-proactive-controls/#div-numbering)) | G28: Not Applicable
A29: Data Protection and Privacy Architecture | B29: 1.8.1 | C29: 2 | F29: Verify that all sensitive data is identified and classified into protection levels. | G29: Not Applicable
B30: 1.8.2 | C30: 2 | F30: Verify that all protection levels have an associated set of protection requirements, such as encryption requirements, integrity requirements, retention, privacy and other confidentiality requirements, and that these are applied in the architecture. | G30: Not Applicable
A31: Communications Architecture | B31: 1.9.1 | C31: 2 | D31: 319 | F31: Verify the application encrypts communications between components, particularly when these components are in different containers, systems, sites, or cloud providers. ([C3](https://owasp.org/www-project-proactive-controls/#div-numbering)) | G31: Non-valid | H31: https://github.com/IsepMartimOliveira/desofs2025_wed_ffs_4/blob/docs/phase1/src/main/java/com/example/psoft_22_23_project/configuration/SecurityConfig.java | I31: App uses HTTP conections. To implement
B32: 1.9.2 | C32: 2 | D32: 295 | F32: Verify that application components verify the authenticity of each side in a communication link to prevent person-in-the-middle attacks. For example, application components should validate TLS certificates and chains. | G32: Non-valid | H32: https://github.com/IsepMartimOliveira/desofs2025_wed_ffs_4/blob/docs/phase1/src/main/java/com/example/psoft_22_23_project/configuration/SecurityConfig.java | I32: App uses HTTP conections
A33: Malicious Software Architecture | B33: 1.10.1 | C33: 2 | D33: 284 | F33: Verify that a source code control system is in use, with procedures to ensure that check-ins are accompanied by issues or change tickets. The source code control system should have access control and identifiable users to allow traceability of any changes. | G33: Valid | H33: https://github.com/IsepMartimOliveira/desofs2025_wed_ffs_4 | I33: Git and Github are used
A34: Business Logic Architecture | B34: 1.11.1 | C34: 2 | D34: 1059 | F34: Verify the definition and documentation of all application components in terms of the business or security functions they provide. | G34: Valid | H34: https://github.com/IsepMartimOliveira/desofs2025_wed_ffs_4/tree/main/docs | I34: All application components and functionalities are defined and documented
B35: 1.11.2 | C35: 2 | D35: 362 | F35: Verify that all high-value business logic flows, including authentication, session management and access control, do not share unsynchronized state. | G35: Valid | H35: https://github.com/IsepMartimOliveira/desofs2025_wed_ffs_4/blob/docs/phase1/src/main/java/com/example/psoft_22_23_project/configuration/SecurityConfig.java | I35: The application operates in a stateless manner, relying on self-contained JWT tokens and a relational database (PostgreSQL) for state management. Authentication, session management, and access control flows do not share unsynchronized state.
B36: 1.11.3 | C36: 2 | D36: 367 | F36: Verify that all high-value business logic flows, including authentication, session management and access control are thread safe and resistant to time-of-check and time-of-use race conditions. | G36: Valid | H36: https://github.com/IsepMartimOliveira/desofs2025_wed_ffs_4/blob/docs/phase1/src/main/java/com/example/psoft_22_23_project/configuration/SecurityConfig.java | I36: The application uses Spring Security, which is inherently thread-safe for managing authentication, session management, and access control. Also uses JWT tokens.
A37: Secure File Upload Architecture | B37: 1.12.1 | C37: 2 | D37: 552 | F37: [DELETED, DUPLICATE OF 12.4.1] | G37: Not Applicable
B38: 1.12.2 | C38: 2 | D38: 646 | F38: Verify that user-uploaded files - if required to be displayed or downloaded from the application - are served by either octet stream downloads, or from an unrelated domain, such as a cloud file storage bucket. Implement a suitable Content Security Policy (CSP) to reduce the risk from XSS vectors or other attacks from the uploaded file. | G38: Valid | H38: https://github.com/IsepMartimOliveira/desofs2025_wed_ffs_4/blob/main/src/main/java/com/example/psoft_22_23_project/filestoragemanagement/service/FileStorageService.java | I38: Line 131 ->156 in Device controller and line 175->176 on SecurityConfig (not yet commited)
A39: API Architecture | F39: This is a placeholder for future architectural requirements. | G39: Not Applicable
A40: Configuration Architecture | B40: 1.14.1 | C40: 2 | D40: 923 | F40: Verify the segregation of components of differing trust levels through well-defined security controls, firewall rules, API gateways, reverse proxies, cloud-based security groups, or similar mechanisms. | G40: Valid | H40: https://github.com/IsepMartimOliveira/desofs2025_wed_ffs_4/blob/docs/phase1/src/main/java/com/example/psoft_22_23_project/configuration/SecurityConfig.java | I40: Only uses RBAC and has permissive CORS policy
B41: 1.14.2 | C41: 2 | D41: 494 | F41: Verify that binary signatures, trusted connections, and verified endpoints are used to deploy binaries to remote devices. | G41: Not Applicable
B42: 1.14.3 | C42: 2 | D42: 1104 | F42: Verify that the build pipeline warns of out-of-date or insecure components and takes appropriate actions. | G42: Valid | H42: https://github.com/IsepMartimOliveira/desofs2025_wed_ffs_4/blob/main/.github/workflows/security_scan.yaml
B43: 1.14.4 | C43: 2 | F43: Verify that the build pipeline contains a build step to automatically build and verify the secure deployment of the application, particularly if the application infrastructure is software defined, such as cloud environment build scripts. | G43: Valid | H43: https://github.com/IsepMartimOliveira/desofs2025_wed_ffs_4/blob/main/.github/workflows/security_scan.yaml
B44: 1.14.5 | C44: 2 | D44: 265 | F44: Verify that application deployments adequately sandbox, containerize and/or isolate at the network level to delay and deter attackers from attacking other applications, especially when they are performing sensitive or dangerous actions such as deserialization. ([C5](https://owasp.org/www-project-proactive-controls/#div-numbering)) | G44: Not Applicable
B45: 1.14.6 | C45: 2 | D45: 477 | F45: Verify the application does not use unsupported, insecure, or deprecated client-side technologies such as NSAPI plugins, Flash, Shockwave, ActiveX, Silverlight, NACL, or client-side Java applets. | G45: Not Applicable

Sheet Authentication
A1: Area | B1: # | C1: ASVS Level | D1: CWE | E1: NIST | F1: Verification Requirement | G1: Valid | H1: Source Code Reference | I1: Comment | J1: Tool Used
A2: Password Security | B2: 2.1.1 | C2: 1 | D2: 521 | E2: 5.1.1.2 | F2: Verify that user set passwords are at least 12 characters in length (after multiple spaces are combined). ([C6](https://owasp.org/www-project-proactive-controls/#div-numbering)) | G2: Valid | H2: https://github.com/IsepMartimOliveira/desofs2025_wed_ffs_4/blob/main/src/main/java/com/example/psoft_22_23_project/usermanagement/api/CreateUserRequest.java | I2: Between line 21 to 24
B3: 2.1.2 | C3: 1 | D3: 521 | E3: 5.1.1.2 | F3: Verify that passwords of at least 64 characters are permitted, and that passwords of more than 128 characters are denied. ([C6](https://owasp.org/www-project-proactive-controls/#div-numbering)) | G3: Not Applicable
B4: 2.1.3 | C4: 1 | D4: 521 | E4: 5.1.1.2 | F4: Verify that password truncation is not performed. However, consecutive multiple spaces may be replaced by a single space. ([C6](https://owasp.org/www-project-proactive-controls/#div-numbering)) | G4: Valid | H4: https://github.com/IsepMartimOliveira/desofs2025_wed_ffs_4/blob/main/src/main/java/com/example/psoft_22_23_project/usermanagement/api/CreateUserRequest.java | I4: Definition of the size of password with minimum and maximum lenght
B5: 2.1.4 | C5: 1 | D5: 521 | E5: 5.1.1.2 | F5: Verify that any printable Unicode character, including language neutral characters such as spaces and Emojis are permitted in passwords. | G5: Valid | H5: https://github.com/IsepMartimOliveira/desofs2025_wed_ffs_4/blob/main/src/main/java/com/example/psoft_22_23_project/usermanagement/api/CreateUserRequest.java | I5: We only use @size(min=12,max=24) annotation so we can use any password in this range
B6: 2.1.5 | C6: 1 | D6: 620 | E6: 5.1.1.2 | F6: Verify users can change their password. | G6: Valid | H6: https://github.com/IsepMartimOliveira/desofs2025_wed_ffs_4/blob/Authentication/src/main/java/com/example/psoft_22_23_project/usermanagement/api/UserController.java | I6: Method ChangePassword
B7: 2.1.6 | C7: 1 | D7: 620 | E7: 5.1.1.2 | F7: Verify that password change functionality requires the user's current and new password. | G7: Valid | H7: https://github.com/IsepMartimOliveira/desofs2025_wed_ffs_4/blob/Authentication/src/main/java/com/example/psoft_22_23_project/usermanagement/services/UserService.java | I7: Method ChangePassword
B8: 2.1.7 | C8: 1 | D8: 521 | E8: 5.1.1.2 | F8: Verify that passwords submitted during account registration, login, and password change are checked against a set of breached passwords either locally (such as the top 1,000 or 10,000 most common passwords which match the system's password policy) or using an external API. If using an API a zero knowledge proof or other mechanism should be used to ensure that the plain text password is not sent or used in verifying the breach status of the password. If the password is breached, the application must require the user to set a new non-breached password. ([C6](https://owasp.org/www-project-proactive-controls/#div-numbering)) | G8: Not Applicable
B9: 2.1.8 | C9: 1 | D9: 521 | E9: 5.1.1.2 | F9: Verify that a password strength meter is provided to help users set a stronger password. | G9: Not Applicable
B10: 2.1.9 | C10: 1 | D10: 521 | E10: 5.1.1.2 | F10: Verify that there are no password composition rules limiting the type of characters permitted. There should be no requirement for upper or lower case or numbers or special characters. ([C6](https://owasp.org/www-project-proactive-controls/#div-numbering)) | G10: Valid | H10: https://github.com/IsepMartimOliveira/desofs2025_wed_ffs_4/blob/Authentication/src/main/java/com/example/psoft_22_23_project/usermanagement/api/CreateUserRequest.java | I10: We didn´t have patterns implemented
B11: 2.1.10 | C11: 1 | D11: 263 | E11: 5.1.1.2 | F11: Verify that there are no periodic credential rotation or password history requirements. | G11: Valid | H11: https://github.com/IsepMartimOliveira/desofs2025_wed_ffs_4/blob/Authentication/src/main/java/com/example/psoft_22_23_project/usermanagement/services/UserService.java | I11: Method ChangePassword
B12: 2.1.11 | C12: 1 | D12: 521 | E12: 5.1.1.2 | F12: Verify that "paste" functionality, browser password helpers, and external password managers are permitted. | G12: Not Applicable
B13: 2.1.12 | C13: 1 | D13: 521 | E13: 5.1.1.2 | F13: Verify that the user can choose to either temporarily view the entire masked password, or temporarily view the last typed character of the password on platforms that do not have this as built-in functionality. | G13: Not Applicable
A14: General Authenticator Security | B14: 2.2.1 | C14: 1 | D14: 307 | E14: 5.2.2, 5.1.1.2, 5.1.4.2, 5.1.5.2 | F14: Verify that anti-automation controls are effective at mitigating breached credential testing, brute force, and account lockout attacks. Such controls include blocking the most common breached passwords, soft lockouts, rate limiting, CAPTCHA, ever increasing delays between attempts, IP address restrictions, or risk-based restrictions such as location, first login on a device, recent attempts to unlock the account, or similar. Verify that no more than 100 failed attempts per hour is possible on a single account. | G14: Valid | H14: https://github.com/IsepMartimOliveira/desofs2025_wed_ffs_4/blob/main/src/main/java/com/example/psoft_22_23_project/api/AuthApi.java | I14: Use ip to see if it exceds the number of times defined and if it yes it blocks the user.
B15: 2.2.2 | C15: 1 | D15: 304 | E15: 5.2.10 | F15: Verify that the use of weak authenticators (such as SMS and email) is limited to secondary verification and transaction approval and not as a replacement for more secure authentication methods. Verify that stronger methods are offered before weak methods, users are aware of the risks, or that proper measures are in place to limit the risks of account compromise. | G15: Not Applicable
B16: 2.2.3 | C16: 1 | D16: 620 | F16: Verify that secure notifications are sent to users after updates to authentication details, such as credential resets, email or address changes, logging in from unknown or risky locations. The use of push notifications - rather than SMS or email - is preferred, but in the absence of push notifications, SMS or email is acceptable as long as no sensitive information is disclosed in the notification. | G16: Not Applicable
B17: 2.2.4 | C17: 3 | D17: 308 | E17: 5.2.5 | F17: Verify impersonation resistance against phishing, such as the use of multi-factor authentication, cryptographic devices with intent (such as connected keys with a push to authenticate), or at higher AAL levels, client-side certificates. | G17: Not Applicable
B18: 2.2.5 | C18: 3 | D18: 319 | E18: 5.2.6 | F18: Verify that where a Credential Service Provider (CSP) and the application verifying authentication are separated, mutually authenticated TLS is in place between the two endpoints. | G18: Not Applicable
B19: 2.2.6 | C19: 3 | D19: 308 | E19: 5.2.8 | F19: Verify replay resistance through the mandated use of One-time Passwords (OTP) devices, cryptographic authenticators, or lookup codes. | G19: Not Applicable
B20: 2.2.7 | C20: 3 | D20: 308 | E20: 5.2.9 | F20: Verify intent to authenticate by requiring the entry of an OTP token or user-initiated action such as a button press on a FIDO hardware key. | G20: Not Applicable
A21: Authenticator Lifecycle | B21: 2.3.1 | C21: 1 | D21: 330 | E21: 5.1.1.2, A. 3 | F21: Verify system generated initial passwords or activation codes SHOULD be securely randomly generated, SHOULD be at least 6 characters long, and MAY contain letters and numbers, and expire after a short period of time. These initial secrets must not be permitted to become the long term password. | G21: Not Applicable
B22: 2.3.2 | C22: 2 | D22: 308 | E22: 6.1.3 | F22: Verify that enrollment and use of user-provided authentication devices are supported, such as a U2F or FIDO tokens. | G22: Not Applicable
B23: 2.3.3 | C23: 2 | D23: 287 | E23: 6.1.4 | F23: Verify that renewal instructions are sent with sufficient time to renew time bound authenticators. | G23: Not Applicable
A24: Credentials Storage | B24: 2.4.1 | C24: 2 | D24: 916 | E24: 5.1.1.2 | F24: Verify that passwords are stored in a form that is resistant to offline attacks. Passwords SHALL be salted and hashed using an approved one-way key derivation or password hashing function. Key derivation and password hashing functions take a password, a salt, and a cost factor as inputs when generating a password hash. ([C6](https://owasp.org/www-project-proactive-controls/#div-numbering)) | G24: Valid | H24: https://github.com/IsepMartimOliveira/desofs2025_wed_ffs_4/blob/main/src/main/java/com/example/psoft_22_23_project/usermanagement/services/UserService.java | I24: line 126
B25: 2.4.2 | C25: 2 | D25: 916 | E25: 5.1.1.2 | F25: Verify that the salt is at least 32 bits in length and be chosen arbitrarily to minimize salt value collisions among stored hashes. For each credential, a unique salt value and the resulting hash SHALL be stored. ([C6](https://owasp.org/www-project-proactive-controls/#div-numbering)) | G25: Valid | H25: https://github.com/IsepMartimOliveira/desofs2025_wed_ffs_4/blob/main/src/main/java/com/example/psoft_22_23_project/configuration/SecurityConfig.java | I25: line 233. BCryptPasswordEncoder already generates a 128 bit salt
B26: 2.4.3 | C26: 2 | D26: 916 | E26: 5.1.1.2 | F26: Verify that if PBKDF2 is used, the iteration count SHOULD be as large as verification server performance will allow, typically at least 100,000 iterations. ([C6](https://owasp.org/www-project-proactive-controls/#div-numbering)) | G26: Not Applicable
B27: 2.4.4 | C27: 2 | D27: 916 | E27: 5.1.1.2 | F27: Verify that if bcrypt is used, the work factor SHOULD be as large as verification server performance will allow, with a minimum of 10. ([C6](https://owasp.org/www-project-proactive-controls/#div-numbering)) | G27: Valid | H27: https://github.com/IsepMartimOliveira/desofs2025_wed_ffs_4/blob/main/src/main/java/com/example/psoft_22_23_project/configuration/SecurityConfig.java | I27: line 233. BCryptPasswordEncoder by default as a work facto of 10
B28: 2.4.5 | C28: 2 | D28: 916 | E28: 5.1.1.2 | F28: Verify that an additional iteration of a key derivation function is performed, using a salt value that is secret and known only to the verifier. Generate the salt value using an approved random bit generator [SP 800-90Ar1] and provide at least the minimum security strength specified in the latest revision of SP 800-131A. The secret salt value SHALL be stored separately from the hashed passwords (e.g., in a specialized device like a hardware security module). | G28: Not Applicable
A29: Credential Recovery | B29: 2.5.1 | C29: 1 | D29: 640 | E29: 5.1.1.2 | F29: Verify that a system generated initial activation or recovery secret is not sent in clear text to the user. ([C6](https://owasp.org/www-project-proactive-controls/#div-numbering)) | G29: Valid
B30: 2.5.2 | C30: 1 | D30: 640 | E30: 5.1.1.2 | F30: Verify password hints or knowledge-based authentication (so-called "secret questions") are not present. | G30: Not Applicable
B31: 2.5.3 | C31: 1 | D31: 640 | E31: 5.1.1.2 | F31: Verify password credential recovery does not reveal the current password in any way. ([C6](https://owasp.org/www-project-proactive-controls/#div-numbering)) | G31: Valid | I31: It asks for the previous passoword but doenst show it
B32: 2.5.4 | C32: 1 | D32: 16 | E32: 5.1.1.2, A. 3 | F32: Verify shared or default accounts are not present (e.g. "root", "admin", or "sa"). | G32: Valid | I32: Changed the bootstrap so it no longer creates a admin account
B33: 2.5.5 | C33: 1 | D33: 304 | E33: 6.1.2.3 | F33: Verify that if an authentication factor is changed or replaced, that the user is notified of this event. | G33: Valid | H33: https://github.com/IsepMartimOliveira/desofs2025_wed_ffs_4/blob/main/src/main/java/com/example/psoft_22_23_project/usermanagement/api/UserController.java | I33: User is notified when password is changed.Line 133-138
B34: 2.5.6 | C34: 1 | D34: 640 | E34: 5.1.1.2 | F34: Verify forgotten password, and other recovery paths use a secure recovery mechanism, such as time-based OTP (TOTP) or other soft token, mobile push, or another offline recovery mechanism. ([C6](https://owasp.org/www-project-proactive-controls/#div-numbering)) | G34: Not Applicable
B35: 2.5.7 | C35: 2 | D35: 308 | E35: 6.1.2.3 | F35: Verify that if OTP or multi-factor authentication factors are lost, that evidence of identity proofing is performed at the same level as during enrollment. | G35: Not Applicable
A36: Look-up Secret Verifier | B36: 2.6.1 | C36: 2 | D36: 308 | E36: 5.1.2.2 | F36: Verify that lookup secrets can be used only once. | G36: Not Applicable
B37: 2.6.2 | C37: 2 | D37: 330 | E37: 5.1.2.2 | F37: Verify that lookup secrets have sufficient randomness (112 bits of entropy), or if less than 112 bits of entropy, salted with a unique and random 32-bit salt and hashed with an approved one-way hash. | G37: Not Applicable
B38: 2.6.3 | C38: 2 | D38: 310 | E38: 5.1.2.2 | F38: Verify that lookup secrets are resistant to offline attacks, such as predictable values. | G38: Not Applicable
A39: Out of Band Verifier | B39: 2.7.1 | C39: 1 | D39: 287 | E39: 5.1.3.2 | F39: Verify that clear text out of band (NIST "restricted") authenticators, such as SMS or PSTN, are not offered by default, and stronger alternatives such as push notifications are offered first. | G39: Not Applicable
B40: 2.7.2 | C40: 1 | D40: 287 | E40: 5.1.3.2 | F40: Verify that the out of band verifier expires out of band authentication requests, codes, or tokens after 10 minutes. | G40: Not Applicable
B41: 2.7.3 | C41: 1 | D41: 287 | E41: 5.1.3.2 | F41: Verify that the out of band verifier authentication requests, codes, or tokens are only usable once, and only for the original authentication request. | G41: Not Applicable
B42: 2.7.4 | C42: 1 | D42: 523 | E42: 5.1.3.2 | F42: Verify that the out of band authenticator and verifier communicates over a secure independent channel. | G42: Not Applicable
B43: 2.7.5 | C43: 2 | D43: 256 | E43: 5.1.3.2 | F43: Verify that the out of band verifier retains only a hashed version of the authentication code. | G43: Not Applicable
B44: 2.7.6 | C44: 2 | D44: 310 | E44: 5.1.3.2 | F44: Verify that the initial authentication code is generated by a secure random number generator, containing at least 20 bits of entropy (typically a six digital random number is sufficient). | G44: Not Applicable
A45: One Time Verifier | B45: 2.8.1 | C45: 1 | D45: 613 | E45: 5.1.4.2, 5.1.5.2 | F45: Verify that time-based OTPs have a defined lifetime before expiring. | G45: Not Applicable
B46: 2.8.2 | C46: 2 | D46: 320 | E46: 5.1.4.2, 5.1.5.2 | F46: Verify that symmetric keys used to verify submitted OTPs are highly protected, such as by using a hardware security module or secure operating system based key storage. | G46: Not Applicable
B47: 2.8.3 | C47: 2 | D47: 326 | E47: 5.1.4.2, 5.1.5.2 | F47: Verify that approved cryptographic algorithms are used in the generation, seeding, and verification of OTPs. | G47: Not Applicable
B48: 2.8.4 | C48: 2 | D48: 287 | E48: 5.1.4.2, 5.1.5.2 | F48: Verify that time-based OTP can be used only once within the validity period. | G48: Not Applicable
B49: 2.8.5 | C49: 2 | D49: 287 | E49: 5.1.5.2 | F49: Verify that if a time-based multi-factor OTP token is re-used during the validity period, it is logged and rejected with secure notifications being sent to the holder of the device. | G49: Not Applicable
B50: 2.8.6 | C50: 2 | D50: 613 | E50: 5.2.1 | F50: Verify physical single-factor OTP generator can be revoked in case of theft or other loss. Ensure that revocation is immediately effective across logged in sessions, regardless of location. | G50: Not Applicable
B51: 2.8.7 | C51: 3 | D51: 308 | E51: 5.2.3 | F51: Verify that biometric authenticators are limited to use only as secondary factors in conjunction with either something you have and something you know. | G51: Not Applicable
A52: Cryptographic Verifier | B52: 2.9.1 | C52: 2 | D52: 320 | E52: 5.1.7.2 | F52: Verify that cryptographic keys used in verification are stored securely and protected against disclosure, such as using a Trusted Platform Module (TPM) or Hardware Security Module (HSM), or an OS service that can use this secure storage. | G52: Not Applicable
B53: 2.9.2 | C53: 2 | D53: 330 | E53: 5.1.7.2 | F53: Verify that the challenge nonce is at least 64 bits in length, and statistically unique or unique over the lifetime of the cryptographic device. | G53: Not Applicable
B54: 2.9.3 | C54: 2 | D54: 327 | E54: 5.1.7.2 | F54: Verify that approved cryptographic algorithms are used in the generation, seeding, and verification. | G54: Not Applicable
A55: Service Authentication | B55: 2.10.1 | C55: LVL2: OS assisted, LVL3: HSM | D55: 287 | E55: 5.1.1.1 | F55: Verify that intra-service secrets do not rely on unchanging credentials such as passwords, API keys or shared accounts with privileged access. | G55: Not Applicable
B56: 2.10.2 | C56: LVL2: OS assisted, LVL3: HSM | D56: 255 | E56: 5.1.1.1 | F56: Verify that if passwords are required for service authentication, the service account used is not a default credential. (e.g. root/root or admin/admin are default in some services during installation). | G56: Valid | I56: No default password are used like admin,root etc..
B57: 2.10.3 | C57: LVL2: OS assisted, LVL3: HSM | D57: 522 | E57: 5.1.1.1 | F57: Verify that passwords are stored with sufficient protection to prevent offline recovery attacks, including local system access. | G57: Not Applicable
B58: 2.10.4 | C58: LVL2: OS assisted, LVL3: HSM | D58: 798 | F58: Verify passwords, integrations with databases and third-party systems, seeds and internal secrets, and API keys are managed securely and not included in the source code or stored within source code repositories. Such storage SHOULD resist offline attacks. The use of a secure software key store (L1), hardware TPM, or an HSM (L3) is recommended for password storage. | G58: Not Applicable

Sheet Session Management
A1: Area | B1: # | C1: ASVS Level | D1: CWE | E1: NIST | F1: Verification Requirement | G1: Valid | H1: Source Code Reference | I1: Comment | J1: Tool Used
A2: Fundamental Session Management Security | B2: 3.1.1 | C2: 1 | D2: 598 | F2: Verify the application never reveals session tokens in URL parameters or error messages. | G2: Valid | I2: It is used generic message witout much information
A3: Session Binding | B3: 3.2.1 | C3: 1 | D3: 384 | E3: 7.1 | F3: Verify the application generates a new session token on user authentication. ([C6](https://www.owasp.org/index.php/OWASP_Proactive_Controls#tab=Formal_Numbering)) | G3: Valid | H3: https://github.com/IsepMartimOliveira/desofs2025_wed_ffs_4/blob/main/src/main/java/com/example/psoft_22_23_project/configuration/JwtService.java | I3: The application generates a new JWT (JSON Web Token) upon each user authentication. This token has a maximum validity of 10 minutes
B4: 3.2.2 | C4: 1 | D4: 331 | E4: 7.1 | F4: Verify that session tokens possess at least 64 bits of entropy. ([C6](https://www.owasp.org/index.php/OWASP_Proactive_Controls#tab=Formal_Numbering)) | G4: Valid | H4: https://github.com/IsepMartimOliveira/desofs2025_wed_ffs_4/blob/main/src/main/java/com/example/psoft_22_23_project/configuration/SecurityConfig.java | I4: The system uses RSA-signed JWTs with cryptographically secure keys, ensuring each token exceeds the 64-bit entropy requirement. Line 206-210
B5: 3.2.3 | C5: 1 | D5: 539 | E5: 7.1 | F5: Verify the application only stores session tokens in the browser using secure methods such as appropriately secured cookies (see section 3.4) or HTML 5 session storage. | G5: Not Applicable | I5: No front-end
B6: 3.2.4 | C6: 2 | D6: 331 | E6: 7.1 | F6: Verify that session tokens are generated using approved cryptographic algorithms. ([C6](https://www.owasp.org/index.php/OWASP_Proactive_Controls#tab=Formal_Numbering)) | G6: Valid | H6: https://github.com/IsepMartimOliveira/desofs2025_wed_ffs_4/blob/main/src/main/java/com/example/psoft_22_23_project/configuration/SecurityConfig.java | I6: The application generates JWT tokens using the RSA algorithm via the Nimbus JOSE+JWT library, which is an OWASP-approved cryptographic standard for secure token generation. Line 209
A7: Session Termination | B7: 3.3.1 | C7: 1 | D7: 613 | E7: 7.1 | F7: Verify that logout and expiration invalidate the session token, such that the back button or a downstream relying party does not resume an authenticated session, including across relying parties. ([C6](https://owasp.org/www-project-proactive-controls/#div-numbering)) | G7: Not Applicable | I7: No logout
B8: 3.3.2 | C8: 1 | D8: 613 | E8: 7.2 | F8: If authenticators permit users to remain logged in, verify that re-authentication occurs periodically both when actively used or after an idle period. ([C6](https://owasp.org/www-project-proactive-controls/#div-numbering)) * L1: 30 days * L2: 12 hours or 30 minutes of inactivity, 2FA optional * L3: 12 hours or 15 minutes of inactivity, with 2FA | G8: Valid | H8: https://github.com/IsepMartimOliveira/desofs2025_wed_ffs_4/blob/main/src/main/java/com/example/psoft_22_23_project/configuration/JwtService.java | I8: Expires after 10 minutos.Line 43
B9: 3.3.3 | C9: 2 | D9: 613 | F9: Verify that the application gives the option to terminate all other active sessions after a successful password change (including change via password reset/recovery), and that this is effective across the application, federated login (if present), and any relying parties. | G9: Not Applicable
B10: 3.3.4 | C10: 2 | D10: 613 | E10: 7.1 | F10: Verify that users are able to view and (having re-entered login credentials) log out of any or all currently active sessions and devices. | G10: Not Applicable
A11: Cookie-based Session Management | B11: 3.4.1 | C11: 1 | D11: 614 | E11: 7.1.1 | F11: Verify that cookie-based session tokens have the 'Secure' attribute set. ([C6](https://owasp.org/www-project-proactive-controls/#div-numbering)) | G11: Not Applicable | I11: No Front-end
B12: 3.4.2 | C12: 1 | D12: 1004 | E12: 7.1.1 | F12: Verify that cookie-based session tokens have the 'HttpOnly' attribute set. ([C6](https://owasp.org/www-project-proactive-controls/#div-numbering)) | G12: Not Applicable | I12: No Front-end
B13: 3.4.3 | C13: 1 | D13: 16 | E13: 7.1.1 | F13: Verify that cookie-based session tokens utilize the 'SameSite' attribute to limit exposure to cross-site request forgery attacks. ([C6](https://owasp.org/www-project-proactive-controls/#div-numbering)) | G13: Not Applicable | I13: No Front-end
B14: 3.4.4 | C14: 1 | D14: 16 | E14: 7.1.1 | F14: Verify that cookie-based session tokens use the "__Host-" prefix so cookies are only sent to the host that initially set the cookie. | G14: Not Applicable | I14: No Front-end
B15: 3.4.5 | C15: 1 | D15: 16 | E15: 7.1.1 | F15: Verify that if the application is published under a domain name with other applications that set or use session cookies that might disclose the session cookies, set the path attribute in cookie-based session tokens using the most precise path possible. ([C6](https://owasp.org/www-project-proactive-controls/#div-numbering)) | G15: Not Applicable | I15: No Front-end
A16: Token-based Session Management | B16: 3.5.1 | C16: 2 | D16: 290 | E16: 7.1.2 | F16: Verify the application allows users to revoke OAuth tokens that form trust relationships with linked applications. | G16: Not Applicable | I16: Our application does not currently use OAuth or support third-party integrations. All authentication is handled internally using JWT tokens.
B17: 3.5.2 | C17: 2 | D17: 798 | F17: Verify the application uses session tokens rather than static API secrets and keys, except with legacy implementations. | G17: Valid | H17: https://github.com/IsepMartimOliveira/desofs2025_wed_ffs_4/blob/main/src/main/java/com/example/psoft_22_23_project/configuration/SecurityConfig.java | I17: We use JWT tokens instead of static API keys because they are more secure, support short lifespans, and don't require storing secrets on the server.
B18: 3.5.3 | C18: 2 | D18: 345 | F18: Verify that stateless session tokens use digital signatures, encryption, and other countermeasures to protect against tampering, enveloping, replay, null cipher, and key substitution attacks. | G18: Valid | H18: https://github.com/IsepMartimOliveira/desofs2025_wed_ffs_4/blob/main/src/main/java/com/example/psoft_22_23_project/configuration/SecurityConfig.java | I18: The JWT tokens are digitally signed with RSA keys, preventing tampering and ensuring token integrity. This meets the requirement for protecting stateless session tokens against common attacks.
A19: Federated Re-authentication | B19: 3.6.1 | C19: 3 | D19: 613 | E19: 7.2.1 | F19: Verify that Relying Parties (RPs) specify the maximum authentication time to Credential Service Providers (CSPs) and that CSPs re-authenticate the subscriber if they haven't used a session within that period. | G19: Not Applicable
B20: 3.6.2 | C20: 3 | D20: 613 | E20: 7.2.1 | F20: Verify that Credential Service Providers (CSPs) inform Relying Parties (RPs) of the last authentication event, to allow RPs to determine if they need to re-authenticate the user. | G20: Not Applicable
A21: Defenses Against Session Management Exploits | B21: 3.7.1 | C21: 1 | D21: 778 | F21: Verify the application ensures a valid login session or requires re-authentication or secondary verification before allowing any sensitive transactions or account modifications. | G21: Valid | I21: This code makes sure only a logged-in user can do sensitive actions by always getting the user from the current login session (getCurrentAuthenticatedUser() method, around line 263)

Sheet Access Control
A1: Area | B1: # | C1: ASVS Level | D1: CWE | E1: NIST | F1: Verification Requirement | G1: Valid | H1: Source Code Reference | I1: Comment | J1: Tool Used
A2: General Access Control Design | B2: 4.1.1 | C2: 1 | D2: 602 | F2: Verify that the application enforces access control rules on a trusted service layer, especially if client-side access control is present and could be bypassed. | G2: Valid | H2: https://github.com/IsepMartimOliveira/desofs2025_wed_ffs_4/blob/main/src/main/java/com/example/psoft_22_23_project/configuration/SecurityConfig.java | I2: Uses Role-Based Access Control (RBAC) with Spring Security annotations and filters at the server level. Access decisions are enforced using a trusted service layer based on JWT-authenticated roles.
B3: 4.1.2 | C3: 1 | D3: 639 | F3: Verify that all user and data attributes and policy information used by access controls cannot be manipulated by end users unless specifically authorized. | G3: Valid | H3: https://github.com/IsepMartimOliveira/desofs2025_wed_ffs_4/blob/main/src/main/java/com/example/psoft_22_23_project/configuration/SecurityConfig.java | I3: JWT tokens are validated and parsed server-side using JwtDecoder and JwtAuthenticationConverter. Claims such as roles are extracted securely and used to enforce access policies.
B4: 4.1.3 | C4: 1 | D4: 285 | F4: Verify that the principle of least privilege exists - users should only be able to access functions, data files, URLs, controllers, services, and other resources, for which they possess specific authorization. This implies protection against spoofing and elevation of privilege. ([C7](https://owasp.org/www-project-proactive-controls/#div-numbering)) | G4: Valid | H4: https://github.com/IsepMartimOliveira/desofs2025_wed_ffs_4/blob/main/src/main/java/com/example/psoft_22_23_project/configuration/SecurityConfig.java | I4: Access to API endpoints is restricted using hasRole(...) and permitAll() for minimal exposure. Roles are enforced with JWT claims, ensuring users only access what they're authorized to.
B5: 4.1.4 | C5: 1 | D5: 276 | F5: [DELETED, DUPLICATE OF 4.1.3] | G5: Not Applicable
B6: 4.1.5 | C6: 1 | D6: 285 | F6: Verify that access controls fail securely including when an exception occurs. ([C10](https://owasp.org/www-project-proactive-controls/#div-numbering)) | G6: Valid | H6: https://github.com/IsepMartimOliveira/desofs2025_wed_ffs_4/blob/main/src/main/java/com/example/psoft_22_23_project/configuration/SecurityConfig.java | I6: a user is unauthenticated, a 401 Unauthorized is returned. If a user is authenticated but lacks permission, a 403 Forbidden is returned. Configured using Spring Security's BearerTokenAuthenticationEntryPoint and BearerTokenAccessDeniedHandler.
A7: Operation Level Access Control | B7: 4.2.1 | C7: 1 | D7: 639 | F7: Verify that sensitive data and APIs are protected against Insecure Direct Object Reference (IDOR) attacks targeting creation, reading, updating and deletion of records, such as creating or updating someone else's record, viewing everyone's records, or deleting all records. | G7: Not Applicable
B8: 4.2.2 | C8: 1 | D8: 352 | F8: Verify that the application or framework enforces a strong anti-CSRF mechanism to protect authenticated functionality, and effective anti-automation or anti-CSRF protects unauthenticated functionality. | G8: Not Applicable | H8: https://github.com/IsepMartimOliveira/desofs2025_wed_ffs_4/blob/main/src/main/java/com/example/psoft_22_23_project/configuration/SecurityConfig.java | I8: Comunicates with the backend via HTTP APIs using JWT in the Authorization header
A9: Other Access Control Considerations | B9: 4.3.1 | C9: 1 | D9: 419 | F9: Verify administrative interfaces use appropriate multi-factor authentication to prevent unauthorized use. | G9: Not Applicable | I9: No multi-factor authentication (MFA) is implemented or required for administrative interfaces at this time.
B10: 4.3.2 | C10: 1 | D10: 548 | F10: Verify that directory browsing is disabled unless deliberately desired. Additionally, applications should not allow discovery or disclosure of file or directory metadata, such as Thumbs.db, .DS_Store, .git or .svn folders. | G10: Valid | I10: The Spring Boot embedded server disables directory browsing by default. No static file exposure or folder listings are enabled.
B11: 4.3.3 | C11: 2 | D11: 732 | F11: Verify the application has additional authorization (such as step up or adaptive authentication) for lower value systems, and / or segregation of duties for high value applications to enforce anti-fraud controls as per the risk of application and past fraud. | G11: Not Applicable | I11: he application does not require step-up authentication or additional anti-fraud controls at this time, as it's not classified as a high-value or high-risk application

Sheet Validation, Sanitization and En
A1: Area | B1: # | C1: ASVS Level | D1: CWE | E1: NIST | F1: Verification Requirement | G1: Valid | H1: Source Code Reference | I1: Comment | J1: Tool Used
A2: Input Validation | B2: 5.1.1 | C2: 1 | D2: 235 | F2: Verify that the application has defenses against HTTP parameter pollution attacks, particularly if the application framework makes no distinction about the source of request parameters (GET, POST, cookies, headers, or environment variables). | G2: Not Applicable
B3: 5.1.2 | C3: 1 | D3: 915 | F3: Verify that frameworks protect against mass parameter assignment attacks, or that the application has countermeasures to protect against unsafe parameter assignment, such as marking fields private or similar. ([C5](https://owasp.org/www-project-proactive-controls/#div-numbering)) | G3: Valid | H3: https://github.com/IsepMartimOliveira/desofs2025_wed_ffs_4/blob/main/src/main/java/com/example/psoft_22_23_project/usermanagement/api/CreateUserRequest.java | I3: Uses DTO(All), use initiateBinder(Subs),IgnoringUnkow fields(Subs)
B4: 5.1.3 | C4: 1 | D4: 20 | F4: Verify that all input (HTML form fields, REST requests, URL parameters, HTTP headers, cookies, batch files, RSS feeds, etc) is validated using positive validation (allow lists). ([C5](https://owasp.org/www-project-proactive-controls/#div-numbering)) | G4: Valid | H4: https://github.com/IsepMartimOliveira/desofs2025_wed_ffs_4/blob/main/src/main/java/com/example/psoft_22_23_project/plansmanagement/api/PlansController.java | I4: Validates input using Bean Validation Annotations like:@RequestBody,@Valid. Validating using @Regex, @Min, @Max on DTO.
B5: 5.1.4 | C5: 1 | D5: 20 | F5: Verify that structured data is strongly typed and validated against a defined schema including allowed characters, length and pattern (e.g. credit card numbers, e-mail addresses, telephone numbers, or validating that two related fields are reasonable, such as checking that suburb and zip/postcode match). ([C5](https://owasp.org/www-project-proactive-controls/#div-numbering)) | G5: Valid | H5: https://github.com/IsepMartimOliveira/desofs2025_wed_ffs_4/blob/main/src/main/java/com/example/psoft_22_23_project/plansmanagement/api/CreatePlanRequest.java | I5: DTO Validation,Header validation(if-match),@InitBinder usage
B6: 5.1.5 | C6: 1 | D6: 601 | F6: Verify that URL redirects and forwards only allow destinations which appear on an allow list, or show a warning when redirecting to potentially untrusted content. | G6: Not Applicable
A7: Sanitization and Sandboxing | B7: 5.2.1 | C7: 1 | D7: 116 | F7: Verify that all untrusted HTML input from WYSIWYG editors or similar is properly sanitized with an HTML sanitizer library or framework feature. ([C5](https://owasp.org/www-project-proactive-controls/#div-numbering)) | G7: Not Applicable
B8: 5.2.2 | C8: 1 | D8: 138 | F8: Verify that unstructured data is sanitized to enforce safety measures such as allowed characters and length. | G8: Valid | H8: https://github.com/IsepMartimOliveira/desofs2025_wed_ffs_4/blob/main/src/main/java/com/example/psoft_22_23_project/usermanagement/model/User.java | I8: Validate using Bean Validation
B9: 5.2.3 | C9: 1 | D9: 147 | F9: Verify that the application sanitizes user input before passing to mail systems to protect against SMTP or IMAP injection. | G9: Not Applicable
B10: 5.2.4 | C10: 1 | D10: 95 | F10: Verify that the application avoids the use of eval() or other dynamic code execution features. Where there is no alternative, any user input being included must be sanitized or sandboxed before being executed. | G10: Valid | H10: https://github.com/IsepMartimOliveira/desofs2025_wed_ffs_4/blob/main/src/main/java/com/example/psoft_22_23_project/filestoragemanagement/sanitize/SanitizeImage.java | I10: Application blocks all command injection patterns (|, &, ;, $) and search confirms zero eval/Runtime/ScriptEngine usage - SanitizeImage.java
B11: 5.2.5 | C11: 1 | D11: 94 | F11: Verify that the application protects against template injection attacks by ensuring that any user input being included is sanitized or sandboxed. | G11: Valid | I11: Uses RBAC,JWT tokens
B12: 5.2.6 | C12: 1 | D12: 918 | F12: Verify that the application protects against SSRF attacks, by validating or sanitizing untrusted data or HTTP file metadata, such as filenames and URL input fields, and uses allow lists of protocols, domains, paths and ports. | G12: Valid | H12: https://github.com/IsepMartimOliveira/desofs2025_wed_ffs_4/blob/main/src/main/java/com/example/psoft_22_23_project/filestoragemanagement/sanitize/SanitizeImage.java | I12: Check if uploaded file doesn´t point to remote url
B13: 5.2.7 | C13: 1 | D13: 159 | F13: Verify that the application sanitizes, disables, or sandboxes user-supplied Scalable Vector Graphics (SVG) scriptable content, especially as they relate to XSS resulting from inline scripts, and foreignObject. | G13: Valid | H13: https://github.com/IsepMartimOliveira/desofs2025_wed_ffs_4/blob/main/src/main/java/com/example/psoft_22_23_project/filestoragemanagement/sanitize/SanitizeImage.java | I13: Only alllows jpg,jpeg,png,gif,webp format
B14: 5.2.8 | C14: 1 | D14: 94 | F14: Verify that the application sanitizes, disables, or sandboxes user-supplied scriptable or expression template language content, such as Markdown, CSS or XSL stylesheets, BBCode, or similar. | G14: Valid | H14: https://github.com/IsepMartimOliveira/desofs2025_wed_ffs_4/blob/main/src/main/java/com/example/psoft_22_23_project/filestoragemanagement/sanitize/SanitizeImage.java | I14: Only alllows jpg,jpeg,png,gif,webp format
A15: Output encoding and Injection Prevention | B15: 5.3.1 | C15: 1 | D15: 116 | F15: Verify that output encoding is relevant for the interpreter and context required. For example, use encoders specifically for HTML values, HTML attributes, JavaScript, URL parameters, HTTP headers, SMTP, and others as the context requires, especially from untrusted inputs (e.g. names with Unicode or apostrophes, such as ねこ or O'Hara). ([C4](https://owasp.org/www-project-proactive-controls/#div-numbering)) | G15: Not Applicable
B16: 5.3.2 | C16: 1 | D16: 176 | F16: Verify that output encoding preserves the user's chosen character set and locale, such that any Unicode character point is valid and safely handled. ([C4](https://owasp.org/www-project-proactive-controls/#div-numbering)) | G16: Valid | H16: https://github.com/IsepMartimOliveira/desofs2025_wed_ffs_4/blob/main/src/main/java/com/example/psoft_22_23_project/filestoragemanagement/sanitize/SanitizeImage.java | I16: This class validates file uploads while preserving Unicode character sets and locale.It filters only security-dangerous characters (path traversal, control chars) without altering the original UTF-8 encoding, ensuring user's chosen character set and locale remain intact throughout validation.
B17: 5.3.3 | C17: 1 | D17: 79 | F17: Verify that context-aware, preferably automated - or at worst, manual - output escaping protects against reflected, stored, and DOM based XSS. ([C4](https://owasp.org/www-project-proactive-controls/#div-numbering)) | G17: Not Applicable
B18: 5.3.4 | C18: 1 | D18: 89 | F18: Verify that data selection or database queries (e.g. SQL, HQL, ORM, NoSQL) use parameterized queries, ORMs, entity frameworks, or are otherwise protected from database injection attacks. ([C3](https://owasp.org/www-project-proactive-controls/#div-numbering)) | G18: Valid | H18: https://github.com/IsepMartimOliveira/desofs2025_wed_ffs_4/blob/main/src/main/java/com/example/psoft_22_23_project/plansmanagement/repositories/PlansRepository.java | I18: Uses Spring Data JPA with parameterized queries, preventing SQL injection.
B19: 5.3.5 | C19: 1 | D19: 89 | F19: Verify that where parameterized or safer mechanisms are not present, context-specific output encoding is used to protect against injection attacks, such as the use of SQL escaping to protect against SQL injection. ([C3, C4](https://owasp.org/www-project-proactive-controls/#div-numbering)) | G19: Not Applicable
B20: 5.3.6 | C20: 1 | D20: 830 | F20: Verify that the application protects against JSON injection attacks, JSON eval attacks, and JavaScript expression evaluation. ([C4](https://owasp.org/www-project-proactive-controls/#div-numbering)) | G20: Not Applicable
B21: 5.3.7 | C21: 1 | D21: 943 | F21: Verify that the application protects against LDAP injection vulnerabilities, or that specific security controls to prevent LDAP injection have been implemented. ([C4](https://owasp.org/www-project-proactive-controls/#div-numbering)) | G21: Not Applicable
B22: 5.3.8 | C22: 1 | D22: 78 | F22: Verify that the application protects against OS command injection and that operating system calls use parameterized OS queries or use contextual command line output encoding. ([C4](https://owasp.org/www-project-proactive-controls/#div-numbering)) | G22: Not Applicable
B23: 5.3.9 | C23: 1 | D23: 829 | F23: Verify that the application protects against Local File Inclusion (LFI) or Remote File Inclusion (RFI) attacks. | G23: Valid | H23: https://github.com/IsepMartimOliveira/desofs2025_wed_ffs_4/blob/main/src/main/java/com/example/psoft_22_23_project/filestoragemanagement/sanitize/SanitizeImage.java | I23: inputs, preventing Local and Remote File Inclusion attacks.
B24: 5.3.10 | C24: 1 | D24: 643 | F24: Verify that the application protects against XPath injection or XML injection attacks. ([C4](https://owasp.org/www-project-proactive-controls/#div-numbering)) | G24: Valid | H24: https://github.com/IsepMartimOliveira/desofs2025_wed_ffs_4/blob/main/src/main/java/com/example/psoft_22_23_project/filestoragemanagement/sanitize/SanitizeImage.java | I24: Prevents XML injection by blocking SVG uploads through strict image type whitelisting
A25: Memory, String and Unmanaged Code | B25: 5.4.1 | C25: 2 | D25: 120 | F25: Verify that the application uses memory-safe string, safer memory copy and pointer arithmetic to detect or prevent stack, buffer, or heap overflows. | G25: Not Applicable | I25: The application is developed using a managed language (Java) which inherently provides memory safety and prevents buffer and heap overflows via its runtime environment.
B26: 5.4.2 | C26: 2 | D26: 134 | F26: Verify that format strings do not take potentially hostile input, and are constant. | G26: Not Applicable
B27: 5.4.3 | C27: 2 | D27: 190 | F27: Verify that sign, range, and input validation techniques are used to prevent integer overflows. | G27: Not Applicable
A28: Deserialization Prevention | B28: 5.5.1 | C28: 1 | D28: 502 | F28: Verify that serialized objects use integrity checks or are encrypted to prevent hostile object creation or data tampering. ([C5](https://owasp.org/www-project-proactive-controls/#div-numbering)) | G28: Valid | H28: https://github.com/IsepMartimOliveira/desofs2025_wed_ffs_4/blob/main/src/main/java/com/example/psoft_22_23_project/configuration/SecurityConfig.java | I28: The application uses cryptographic signatures or encryption to ensure serialized data integrity and prevent tampering or hostile object injection.
B29: 5.5.2 | C29: 1 | D29: 611 | F29: Verify that the application correctly restricts XML parsers to only use the most restrictive configuration possible and to ensure that unsafe features such as resolving external entities are disabled to prevent XML eXternal Entity (XXE) attacks. | G29: Valid | H29: https://github.com/IsepMartimOliveira/desofs2025_wed_ffs_4/blob/main/src/main/java/com/example/psoft_22_23_project/filestoragemanagement/sanitize/SanitizeImage.java | I29: The application also uses Apache Tika for file type validation in SanitizeImage.java, providing defense-in-depth against file-based XXE attacks
B30: 5.5.3 | C30: 1 | D30: 502 | F30: Verify that deserialization of untrusted data is avoided or is protected in both custom code and third-party libraries (such as JSON, XML and YAML parsers). | G30: Valid | H30: https://github.com/IsepMartimOliveira/desofs2025_wed_ffs_4/blob/main/src/main/java/com/example/psoft_22_23_project/usermanagement/api/UserController.java | I30: All REST controllers use type-safe DTOs mapped through MapStruct, ensuring controlled deserialization paths without arbitrary object instantiation.
B31: 5.5.4 | C31: 1 | D31: 95 | F31: Verify that when parsing JSON in browsers or JavaScript-based backends, JSON.parse is used to parse the JSON document. Do not use eval() to parse JSON. | G31: Not Applicable

Sheet Stored Cryptography
A1: Area | B1: # | C1: ASVS Level | D1: CWE | E1: NIST | F1: Verification Requirement | G1: Valid | H1: Source Code Reference | I1: Comment | J1: Tool Used
A2: Data Classification | B2: 6.1.1 | C2: 2 | D2: 311 | F2: Verify that regulated private data is stored encrypted while at rest, such as Personally Identifiable Information (PII), sensitive personal information, or data assessed likely to be subject to EU's GDPR. | G2: Valid | H2: "public String encrypt(String plaintext) { if (plaintext == null || plaintext.isEmpty()) { return plaintext; } try { byte[] iv = new byte[ivLength]; secureRandom.nextBytes(iv); Cipher cipher = Cipher.getInstance(transformation); GCMParameterSpec gcmParameterSpec = new GCMParameterSpec(tagLength, iv); cipher.init(Cipher.ENCRYPT_MODE, encryptionKey, gcmParameterSpec); byte[] encryptedData = cipher.doFinal(plaintext.getBytes(StandardCharsets.UTF_8)); ByteBuffer buffer = ByteBuffer.allocate(ivLength + encryptedData.length); buffer.put(iv); buffer.put(encryptedData); return Base64.getEncoder().encodeToString(buffer.array()); } catch (Exception e) { logger.error("Encryption failed", e); throw new RuntimeException("Failed to encrypt data", e); } }" | I2: User location, email, phone number, and age are encrypted before being saved.
B3: 6.1.2 | C3: 2 | D3: 311 | F3: Verify that regulated health data is stored encrypted while at rest, such as medical records, medical device details, or de-anonymized research records. | G3: Not Applicable
B4: 6.1.3 | C4: 2 | D4: 311 | F4: Verify that regulated financial data is stored encrypted while at rest, such as financial accounts, defaults or credit history, tax records, pay history, beneficiaries, or de-anonymized market or research records. | G4: Not Applicable
A5: Algorithms | B5: 6.2.1 | C5: 1 | D5: 310 | F5: Verify that all cryptographic modules fail securely, and errors are handled in a way that does not enable Padding Oracle attacks. | G5: Valid | H5: "public String encrypt(String plaintext) { if (plaintext == null || plaintext.isEmpty()) { return plaintext; } try { byte[] iv = new byte[ivLength]; secureRandom.nextBytes(iv); Cipher cipher = Cipher.getInstance(transformation); GCMParameterSpec gcmParameterSpec = new GCMParameterSpec(tagLength, iv); cipher.init(Cipher.ENCRYPT_MODE, encryptionKey, gcmParameterSpec); byte[] encryptedData = cipher.doFinal(plaintext.getBytes(StandardCharsets.UTF_8)); ByteBuffer buffer = ByteBuffer.allocate(ivLength + encryptedData.length); buffer.put(iv); buffer.put(encryptedData); return Base64.getEncoder().encodeToString(buffer.array()); } catch (Exception e) { logger.error("Encryption failed", e); throw new RuntimeException("Failed to encrypt data", e); } }" | I5: Exceptions with generic error messages are used. Also, GCM is already resistant to Padding Oracle attacks.
B6: 6.2.2 | C6: 2 | D6: 327 | F6: Verify that industry proven or government approved cryptographic algorithms, modes, and libraries are used, instead of custom coded cryptography. ([C8](https://owasp.org/www-project-proactive-controls/#div-numbering)) | G6: Valid | H6: https://github.com/IsepMartimOliveira/desofs2025_wed_ffs_4/blob/main/src/main/java/com/example/psoft_22_23_project/configuration/SecurityConfig.java "@Bean public PasswordEncoder passwordEncoder() { return new BCryptPasswordEncoder(); }" | I6: Bcrypt password encoder is used for password hashing, RSA algorithm is used for JWT encoding/decoding, and AES is used for user data encryption which are industry standard algorithms.
B7: 6.2.3 | C7: 2 | D7: 326 | F7: Verify that encryption initialization vector, cipher configuration, and block modes are configured securely using the latest advice. | G7: Valid | H7: "public String encrypt(String plaintext) { if (plaintext == null || plaintext.isEmpty()) { return plaintext; } try { byte[] iv = new byte[ivLength]; secureRandom.nextBytes(iv); Cipher cipher = Cipher.getInstance(transformation); GCMParameterSpec gcmParameterSpec = new GCMParameterSpec(tagLength, iv); cipher.init(Cipher.ENCRYPT_MODE, encryptionKey, gcmParameterSpec); byte[] encryptedData = cipher.doFinal(plaintext.getBytes(StandardCharsets.UTF_8)); ByteBuffer buffer = ByteBuffer.allocate(ivLength + encryptedData.length); buffer.put(iv); buffer.put(encryptedData); return Base64.getEncoder().encodeToString(buffer.array()); } catch (Exception e) { logger.error("Encryption failed", e); throw new RuntimeException("Failed to encrypt data", e); } }" | I7: AES/GCM is used, along with random generated IV for each encryption with SecureRandom.
B8: 6.2.4 | C8: 2 | D8: 326 | F8: Verify that random number, encryption or hashing algorithms, key lengths, rounds, ciphers or modes, can be reconfigured, upgraded, or swapped at any time, to protect against cryptographic breaks. ([C8](https://owasp.org/www-project-proactive-controls/#div-numbering)) | G8: Valid | H8: https://github.com/IsepMartimOliveira/desofs2025_wed_ffs_4/blob/main/src/main/java/com/example/psoft_22_23_project/configuration/SecurityConfig.java @Bean public JwtEncoder jwtEncoder() { final JWK jwk = new RSAKey.Builder(this.rsaPublicKey).privateKey(this.rsaPrivateKey).build(); final JWKSource<SecurityContext> jwks = new ImmutableJWKSet<>(new JWKSet(jwk)); return new NimbusJwtEncoder(jwks); } // Used by JwtAuthenticationProvider to decode and validate JWT tokens @Bean public JwtDecoder jwtDecoder() { return NimbusJwtDecoder.withPublicKey(this.rsaPublicKey).build(); } | I8: The cryptographic primitives in use (BCrypt for password hashing and RSA for JWT signing) are configured via dependency injection and Spring beans in SecurityConfig.
B9: 6.2.5 | C9: 2 | D9: 326 | F9: Verify that known insecure block modes (i.e. ECB, etc.), padding modes (i.e. PKCS#1 v1.5, etc.), ciphers with small block sizes (i.e. Triple-DES, Blowfish, etc.), and weak hashing algorithms (i.e. MD5, SHA1, etc.) are not used unless required for backwards compatibility. | G9: Valid | H9: https://github.com/IsepMartimOliveira/desofs2025_wed_ffs_4/blob/main/src/main/java/com/example/psoft_22_23_project/configuration/SecurityConfig.java | I9: JWTs are signed with RSA keys via Nimbus JOSE JWT, which does not use insecure block modes like ECB or weak paddings. Passwords are hashed with BCrypt, which is a strong, industry-standard algorithm and does not use weak hash functions like MD5 or SHA1. For user data encryption, AES/GCM is used.
B10: 6.2.6 | C10: 2 | D10: 326 | F10: Verify that nonces, initialization vectors, and other single use numbers must not be used more than once with a given encryption key. The method of generation must be appropriate for the algorithm being used. | G10: Valid | H10: https://github.com/IsepMartimOliveira/desofs2025_wed_ffs_4/blob/main/src/main/java/com/example/psoft_22_23_project/configuration/SecurityConfig.java | I10: Passwords are protected with bcrypt, which generates a unique random salt for each password. This salt is treated as a single-use value (equivalent to a nonce) and is never reused. Also, a new IV is generated for each user data encription.
B11: 6.2.7 | C11: 3 | D11: 326 | F11: Verify that encrypted data is authenticated via signatures, authenticated cipher modes, or HMAC to ensure that ciphertext is not altered by an unauthorized party. | G11: Valid | H11: "@Bean public JwtEncoder jwtEncoder() { final JWK jwk = new RSAKey.Builder(this.rsaPublicKey).privateKey(this.rsaPrivateKey).build(); final JWKSource<SecurityContext> jwks = new ImmutableJWKSet<>(new JWKSet(jwk)); return new NimbusJwtEncoder(jwks); } // Used by JwtAuthenticationProvider to decode and validate JWT tokens @Bean public JwtDecoder jwtDecoder() { return NimbusJwtDecoder.withPublicKey(this.rsaPublicKey).build(); }" | I11: JWTs are signed (authenticated) using RSA, and GCM provides authenticated encription.
B12: 6.2.8 | C12: 3 | D12: 385 | F12: Verify that all cryptographic operations are constant-time, with no 'short-circuit' operations in comparisons, calculations, or returns, to avoid leaking information. | G12: Valid | H12: @Bean_x000D_ public JwtEncoder jwtEncoder() {_x000D_ final JWK jwk = new RSAKey.Builder(this.rsaPublicKey).privateKey(this.rsaPrivateKey).build();_x000D_ final JWKSource<SecurityContext> jwks = new ImmutableJWKSet<>(new JWKSet(jwk));_x000D_ return new NimbusJwtEncoder(jwks);_x000D_ }_x000D_ _x000D_ // Used by JwtAuthenticationProvider to decode and validate JWT tokens_x000D_ @Bean_x000D_ public JwtDecoder jwtDecoder() {_x000D_ return NimbusJwtDecoder.withPublicKey(this.rsaPublicKey).build();_x000D_ } | I12: All cryptographic operations (password hashing with BCrypt and JWT signing/verification with RSA via Nimbus JOSE JWT) are handled by well-established libraries.
A13: Random values | B13: 6.3.1 | C13: 2 | D13: 338 | F13: Verify that all random numbers, random file names, random GUIDs, and random strings are generated using the cryptographic module's approved cryptographically secure random number generator when these random values are intended to be not guessable by an attacker. | G13: Valid | H13: "@Bean public PasswordEncoder passwordEncoder() { return new BCryptPasswordEncoder(); }" | I13: The random salt used in password hashing is generated using a secure random number generator, managed by BCryptPasswordEncoder. Other random values are not security relevant.
B14: 6.3.2 | C14: 2 | D14: 338 | F14: Verify that random GUIDs are created using the GUID v4 algorithm, and a Cryptographically-secure Pseudo-random Number Generator (CSPRNG). GUIDs created using other pseudo-random number generators may be predictable. | G14: Not Applicable | I14: Random UUIDs generated in the project are exclusively used for internal logging or files names that aren't externally accessible without authentication.
B15: 6.3.3 | C15: 3 | D15: 338 | F15: Verify that random numbers are created with proper entropy even when the application is under heavy load, or that the application degrades gracefully in such circumstances. | G15: Valid | H15: https://github.com/IsepMartimOliveira/desofs2025_wed_ffs_4/blob/main/src/main/java/com/example/psoft_22_23_project/configuration/SecurityConfig.java | I15: All cryptographic operations (password hashing with BCrypt and JWT signing/verification with RSA via Nimbus JOSE JWT) use, by default, Spring Security SecureRandom for random number generation.
A16: Secret Management | B16: 6.4.1 | C16: 2 | D16: 798 | F16: Verify that a secrets management solution such as a key vault is used to securely create, store, control access to and destroy secrets. ([C8](https://owasp.org/www-project-proactive-controls/#div-numbering)) | G16: Valid | H16: https://github.com/IsepMartimOliveira/desofs2025_wed_ffs_4/blob/main/.github/workflows/build_and_publish.yaml | I16: Secrets are managed using GitHub Secrets
B17: 6.4.2 | C17: 2 | D17: 320 | F17: Verify that key material is not exposed to the application but instead uses an isolated security module like a vault for cryptographic operations. ([C8](https://owasp.org/www-project-proactive-controls/#div-numbering)) | G17: Non-valid

Sheet Error Handling and Logging
A1: Area | B1: # | C1: ASVS Level | D1: CWE | E1: NIST | F1: Verification Requirement | G1: Valid | H1: Source Code Reference | I1: Comment | J1: Tool Used
A2: Log Content | B2: 7.1.1 | C2: 1 | D2: 532 | F2: Verify that the application does not log credentials or payment details. Session tokens should only be stored in logs in an irreversible, hashed form. ([C9, C10](https://owasp.org/www-project-proactive-controls/#div-numbering)) | G2: Valid | H2: https://github.com/IsepMartimOliveira/desofs2025_wed_ffs_4/blob/main/src/main/java/com/example/psoft_22_23_project/api/AuthApi.java | I2: Inside the try-catch block of the login method
B3: 7.1.2 | C3: 1 | D3: 532 | F3: Verify that the application does not log other sensitive data as defined under local privacy laws or relevant security policy. ([C9](https://owasp.org/www-project-proactive-controls/#div-numbering)) | G3: Valid | H3: https://github.com/IsepMartimOliveira/desofs2025_wed_ffs_4/blob/main/src/main/java/com/example/psoft_22_23_project/api/AuthApi.java | I3: Line 107 (log.info("User {} successfully authenticated from IP {} in {} ms", Utils.sanitize(username), Utils.sanitize(clientIp),duration);)
B4: 7.1.3 | C4: 2 | D4: 778 | F4: Verify that the application logs security relevant events including successful and failed authentication events, access control failures, deserialization failures and input validation failures. ([C5, C7](https://owasp.org/www-project-proactive-controls/#div-numbering)) | G4: Valid | H4: https://github.com/IsepMartimOliveira/desofs2025_wed_ffs_4/blob/main/src/main/java/com/example/psoft_22_23_project/api/AuthApi.java | I4: Line 119 and 120
B5: 7.1.4 | C5: 2 | D5: 778 | F5: Verify that each log event includes necessary information that would allow for a detailed investigation of the timeline when an event happens. ([C9](https://owasp.org/www-project-proactive-controls/#div-numbering)) | G5: Valid | H5: https://github.com/IsepMartimOliveira/desofs2025_wed_ffs_4/blob/main/src/main/java/com/example/psoft_22_23_project/subscriptionsmanagement/api/SubscriptionsController.java | I5: Line 119 and 120
A6: Log Processing | B6: 7.2.1 | C6: 2 | D6: 778 | F6: Verify that all authentication decisions are logged, without storing sensitive session identifiers or passwords. This should include requests with relevant metadata needed for security investigations. | G6: Valid | H6: https://github.com/IsepMartimOliveira/desofs2025_wed_ffs_4/blob/main/src/main/java/com/example/psoft_22_23_project/api/AuthApi.java | I6: Line 107 (log.info("User {} successfully authenticated from IP {} in {} ms", Utils.sanitize(username), Utils.sanitize(clientIp),duration);)
B7: 7.2.2 | C7: 2 | D7: 285 | F7: Verify that all access control decisions can be logged and all failed decisions are logged. This should include requests with relevant metadata needed for security investigations. | G7: Valid | H7: https://github.com/IsepMartimOliveira/desofs2025_wed_ffs_4/blob/main/src/main/java/com/example/psoft_22_23_project/api/AuthApi.java | I7: All the class Auth you can see all failed decisions are logged
A8: Log Protection | B8: 7.3.1 | C8: 2 | D8: 117 | F8: Verify that all logging components appropriately encode data to prevent log injection. ([C9](https://owasp.org/www-project-proactive-controls/#div-numbering)) | G8: Valid | H8: https://github.com/IsepMartimOliveira/desofs2025_wed_ffs_4/blob/main/src/main/java/com/example/psoft_22_23_project/exceptions/GlobalExceptionHandler.java | I8: in all logs of the class
B9: 7.3.2 | C9: 2 | D9: 117 | F9: [DELETED, DUPLICATE OF 7.3.1] | G9: Not Applicable
B10: 7.3.3 | C10: 2 | D10: 200 | F10: Verify that security logs are protected from unauthorized access and modification. ([C9](https://owasp.org/www-project-proactive-controls/#div-numbering)) | G10: Not Applicable
B11: 7.3.4 | C11: 2 | F11: Verify that time sources are synchronized to the correct time and time zone. Strongly consider logging only in UTC if systems are global to assist with post-incident forensic analysis. ([C9](https://owasp.org/www-project-proactive-controls/#div-numbering)) | G11: Not Applicable
A12: Error Handling | B12: 7.4.1 | C12: 1 | D12: 210 | F12: Verify that a generic message is shown when an unexpected or security sensitive error occurs, potentially with a unique ID which support personnel can use to investigate. ([C10](https://owasp.org/www-project-proactive-controls/#div-numbering)) | G12: Valid | H12: https://github.com/IsepMartimOliveira/desofs2025_wed_ffs_4/blob/main/src/main/java/com/example/psoft_22_23_project/exceptions/GlobalExceptionHandler.java | I12: Method handleInternalServerError
B13: 7.4.2 | C13: 2 | D13: 544 | F13: Verify that exception handling (or a functional equivalent) is used across the codebase to account for expected and unexpected error conditions. ([C10](https://owasp.org/www-project-proactive-controls/#div-numbering)) | G13: Valid | H13: https://github.com/IsepMartimOliveira/desofs2025_wed_ffs_4/blob/main/src/main/java/com/example/psoft_22_23_project/api/AuthApi.java | I13: Inside the try-catch block of the login method when you have 2 catches (LockedException and Exception)
B14: 7.4.3 | C14: 2 | D14: 431 | F14: Verify that a "last resort" error handler is defined which will catch all unhandled exceptions. ([C10](https://owasp.org/www-project-proactive-controls/#div-numbering)) | G14: Valid | H14: https://github.com/IsepMartimOliveira/desofs2025_wed_ffs_4/blob/main/src/main/java/com/example/psoft_22_23_project/exceptions/GlobalExceptionHandler.java | I14: Method handleInternalServerError

Sheet Data Protection
A1: Area | B1: # | C1: ASVS Level | D1: CWE | E1: NIST | F1: Verification Requirement | G1: Valid | H1: Source Code Reference | I1: Comment | J1: Tool Used
A2: General Data Protection | B2: 8.1.1 | C2: 2 | D2: 524 | F2: Verify the application protects sensitive data from being cached in server components such as load balancers and application caches. | G2: Not Applicable
B3: 8.1.2 | C3: 2 | D3: 524 | F3: Verify that all cached or temporary copies of sensitive data stored on the server are protected from unauthorized access or purged/invalidated after the authorized user accesses the sensitive data. | G3: Not Applicable
B4: 8.1.3 | C4: 2 | D4: 233 | F4: Verify the application minimizes the number of parameters in a request, such as hidden fields, Ajax variables, cookies and header values. | G4: Valid | H4: https://github.com/IsepMartimOliveira/desofs2025_wed_ffs_4/blob/main/src/main/java/com/example/psoft_22_23_project/dashboardmanagement/api/DashboardController.java | I4: Parameter minimization - Controllers use minimal params with @Valid validation (DashboardController.getDashboardView max 6 params)
B5: 8.1.4 | C5: 2 | D5: 770 | F5: Verify the application can detect and alert on abnormal numbers of requests, such as by IP, user, total per hour or day, or whatever makes sense for the application. | G5: Valid | H5: https://github.com/IsepMartimOliveira/desofs2025_wed_ffs_4/blob/main/src/main/java/com/example/psoft_22_23_project/usermanagement/services/UserService.java | I5: The LoginAttemptService.loginFailed() in LoginAttemptService.java implements request monitoring by tracking attempt counts per user/IP, detecting threshold breaches (5 user, 20 IP), and triggering automatic blocks with security logging.
B6: 8.1.5 | C6: 3 | D6: 19 | F6: Verify that regular backups of important data are performed and that test restoration of data is performed. | G6: Not Applicable
B7: 8.1.6 | C7: 3 | D7: 19 | F7: Verify that backups are stored securely to prevent data from being stolen or corrupted. | G7: Not Applicable
A8: Client-side Data Protection | B8: 8.2.1 | C8: 1 | D8: 525 | F8: Verify the application sets sufficient anti-caching headers so that sensitive data is not cached in modern browsers. | G8: Not Applicable
B9: 8.2.2 | C9: 1 | D9: 922 | F9: Verify that data stored in browser storage (such as localStorage, sessionStorage, IndexedDB, or cookies) does not contain sensitive data. | G9: Not Applicable
B10: 8.2.3 | C10: 1 | D10: 922 | F10: Verify that authenticated data is cleared from client storage, such as the browser DOM, after the client or session is terminated. | G10: Not Applicable
A11: Sensitive Private Data | B11: 8.3.1 | C11: 1 | D11: 319 | F11: Verify that sensitive data is sent to the server in the HTTP message body or headers, and that query string parameters from any HTTP verb do not contain sensitive data. | G11: Not Applicable
B12: 8.3.2 | C12: 1 | D12: 212 | F12: Verify that users have a method to remove or export their data on demand. | G12: Valid | H12: https://github.com/IsepMartimOliveira/desofs2025_wed_ffs_4/blob/Authentication/src/main/java/com/example/psoft_22_23_project/usermanagement/api/UserController.java | I12: Two endpoints were implemented in order for the user to be able to export their personal data in JSON format or request its deletion.
B13: 8.3.3 | C13: 1 | D13: 285 | F13: Verify that users are provided clear language regarding collection and use of supplied personal information and that users have provided opt-in consent for the use of that data before it is used in any way. | G13: Not Applicable
B14: 8.3.4 | C14: 1 | D14: 200 | F14: Verify that all sensitive data created and processed by the application has been identified, and ensure that a policy is in place on how to deal with sensitive data. ([C8](https://owasp.org/www-project-proactive-controls/#div-numbering)) | G14: Valid | H14: https://github.com/IsepMartimOliveira/desofs2025_wed_ffs_4/blob/main/src/main/java/com/example/psoft_22_23_project/usermanagement/services/UserService.java | I14: https://github.com/IsepMartimOliveira/desofs2025_wed_ffs_4/blob/main/src/main/java/com/example/psoft_22_23_project/usermanagement/services/UserService.java
B15: 8.3.5 | C15: 2 | D15: 532 | F15: Verify accessing sensitive data is audited (without logging the sensitive data itself), if the data is collected under relevant data protection directives or where logging of access is required. | G15: Valid | H15: https://github.com/IsepMartimOliveira/desofs2025_wed_ffs_4/blob/main/src/main/java/com/example/psoft_22_23_project/usermanagement/services/UserService.java | I15: https://github.com/IsepMartimOliveira/desofs2025_wed_ffs_4/blob/main/src/main/java/com/example/psoft_22_23_project/usermanagement/services/UserService.java
B16: 8.3.6 | C16: 2 | D16: 226 | F16: Verify that sensitive information contained in memory is overwritten as soon as it is no longer required to mitigate memory dumping attacks, using zeroes or random data. | G16: Valid | H16: https://github.com/IsepMartimOliveira/desofs2025_wed_ffs_4/blob/main/src/main/java/com/example/psoft_22_23_project/api/AuthApi.java | I16: https://github.com/IsepMartimOliveira/desofs2025_wed_ffs_4/blob/main/src/main/java/com/example/psoft_22_23_project/api/AuthApi.java
B17: 8.3.7 | C17: 2 | D17: 327 | F17: Verify that sensitive or private information that is required to be encrypted, is encrypted using approved algorithms that provide both confidentiality and integrity. ([C8](https://owasp.org/www-project-proactive-controls/#div-numbering)) | G17: Valid | H17: https://github.com/IsepMartimOliveira/desofs2025_wed_ffs_4/blob/main/src/main/java/com/example/psoft_22_23_project/usermanagement/services/LoginAttemptService.java | I17: https://github.com/IsepMartimOliveira/desofs2025_wed_ffs_4/blob/main/src/main/java/com/example/psoft_22_23_project/usermanagement/services/LoginAttemptService.java
B18: 8.3.8 | C18: 2 | D18: 285 | F18: Verify that sensitive personal information is subject to data retention classification, such that old or out of date data is deleted automatically, on a schedule, or as the situation requires. | G18: Valid | H18: https://github.com/IsepMartimOliveira/desofs2025_wed_ffs_4/blob/main/src/main/java/com/example/psoft_22_23_project/usermanagement/services/UserService.java | I18: https://github.com/IsepMartimOliveira/desofs2025_wed_ffs_4/blob/main/src/main/java/com/example/psoft_22_23_project/usermanagement/services/UserService.java

Sheet Communication
A1: Area | B1: # | C1: ASVS Level | D1: CWE | E1: NIST | F1: Verification Requirement | G1: Valid | H1: Source Code Reference | I1: Comment | J1: Tool Used
A2: Client Communications Security | B2: 9.1.1 | C2: 1 | D2: 319 | F2: Verify that TLS is used for all client connectivity, and does not fall back to insecure or unencrypted communications. ([C8](https://owasp.org/www-project-proactive-controls/#div-numbering)) | G2: Valid | H2: https://github.com/IsepMartimOliveira/desofs2025_wed_ffs_4/blob/main/src/main/resources/application.properties | I2: Enable SSL in application properties
B3: 9.1.2 | C3: 1 | D3: 326 | F3: Verify using up to date TLS testing tools that only strong cipher suites are enabled, with the strongest cipher suites set as preferred. | G3: Valid | H3: https://github.com/IsepMartimOliveira/desofs2025_wed_ffs_4/blob/main/src/main/resources/application.properties | I3: HTTPS is enforced through Spring Boot configuration using a self-signed certificate in keystore.p12. The application is configured to support only TLS 1.2 and 1.3, and to disable all older or insecure protocols. Strong cipher suites are explicitly enabled.
B4: 9.1.3 | C4: 1 | D4: 326 | F4: Verify that only the latest recommended versions of the TLS protocol are enabled, such as TLS 1.2 and TLS 1.3. The latest version of the TLS protocol should be the preferred option. | G4: Valid | H4: https://github.com/IsepMartimOliveira/desofs2025_wed_ffs_4/blob/main/src/main/resources/application.properties | I4: In application.properties we have "server.ssl.enabled-protocols=TLSv1.3,TLSv1.2 "
A5: Server Communication Security | B5: 9.2.1 | C5: 2 | D5: 295 | F5: Verify that connections to and from the server use trusted TLS certificates. Where internally generated or self-signed certificates are used, the server must be configured to only trust specific internal CAs and specific self-signed certificates. All others should be rejected. | G5: Valid | H5: https://github.com/IsepMartimOliveira/desofs2025_wed_ffs_4/blob/main/src/main/resources/application.properties | I5: In application.properties we have "server.ssl.key-store=classpath:keystore.p12"
B6: 9.2.2 | C6: 2 | D6: 319 | F6: Verify that encrypted communications such as TLS is used for all inbound and outbound connections, including for management ports, monitoring, authentication, API, or web service calls, database, cloud, serverless, mainframe, external, and partner connections. The server must not fall back to insecure or unencrypted protocols. | G6: Valid | H6: https://github.com/IsepMartimOliveira/desofs2025_wed_ffs_4/blob/main/src/main/resources/application.properties | I6: In application.properties we have "server.ssl.key-store=classpath:keystore.p12"
B7: 9.2.3 | C7: 2 | D7: 287 | F7: Verify that all encrypted connections to external systems that involve sensitive information or functions are authenticated. | G7: Not Applicable
B8: 9.2.4 | C8: 2 | D8: 299 | F8: Verify that proper certification revocation, such as Online Certificate Status Protocol (OCSP) Stapling, is enabled and configured. | G8: Not Applicable
B9: 9.2.5 | C9: 3 | D9: 544 | F9: Verify that backend TLS connection failures are logged. | G9: Valid | H9: https://github.com/IsepMartimOliveira/desofs2025_wed_ffs_4/blob/main/src/main/resources/application.properties | I9: In application.properties we add logging.level.javax.net.ssl=DEBUG

Sheet Malicious Code
A1: Area | B1: # | C1: ASVS Level | D1: CWE | E1: NIST | F1: Verification Requirement | G1: Valid | H1: Source Code Reference | I1: Comment | J1: Tool Used
A2: Code Integrity | B2: 10.1.1 | C2: 3 | D2: 749 | F2: Verify that a code analysis tool is in use that can detect potentially malicious code, such as time functions, unsafe file operations and network connections. | G2: Valid | H2: https://github.com/IsepMartimOliveira/desofs2025_wed_ffs_4/blob/main/.github/workflows/tests_before_push_main.yaml | I2: We use SonarQube in our pipeline
A3: Malicious Code Search | B3: 10.2.1 | C3: 2 | D3: 359 | F3: Verify that the application source code and third party libraries do not contain unauthorized phone home or data collection capabilities. Where such functionality exists, obtain the user's permission for it to operate before collecting any data. | G3: Valid | H3: https://github.com/IsepMartimOliveira/desofs2025_wed_ffs_4/blob/main/pom.xml | I3: After analyzing the documentation of the third-party libraries and the source code, there is no unauthorized data collection.
B4: 10.2.2 | C4: 2 | D4: 272 | F4: Verify that the application does not ask for unnecessary or excessive permissions to privacy related features or sensors, such as contacts, cameras, microphones, or location. | G4: Not Applicable
B5: 10.2.3 | C5: 3 | D5: 507 | F5: Verify that the application source code and third party libraries do not contain back doors, such as hard-coded or additional undocumented accounts or keys, code obfuscation, undocumented binary blobs, rootkits, or anti-debugging, insecure debugging features, or otherwise out of date, insecure, or hidden functionality that could be used maliciously if discovered. | G5: Not Applicable
B6: 10.2.4 | C6: 3 | D6: 511 | F6: Verify that the application source code and third party libraries do not contain time bombs by searching for date and time related functions. | G6: Not Applicable
B7: 10.2.5 | C7: 3 | D7: 511 | F7: Verify that the application source code and third party libraries do not contain malicious code, such as salami attacks, logic bypasses, or logic bombs. | G7: Not Applicable
B8: 10.2.6 | C8: 3 | D8: 507 | F8: Verify that the application source code and third party libraries do not contain Easter eggs or any other potentially unwanted functionality. | G8: Not Applicable
A9: Application Integrity | B9: 10.3.1 | C9: 1 | D9: 16 | F9: Verify that if the application has a client or server auto-update feature, updates should be obtained over secure channels and digitally signed. The update code must validate the digital signature of the update before installing or executing the update. | G9: Not Applicable
B10: 10.3.2 | C10: 1 | D10: 353 | F10: Verify that the application employs integrity protections, such as code signing or subresource integrity. The application must not load or execute code from untrusted sources, such as loading includes, modules, plugins, code, or libraries from untrusted sources or the Internet. | G10: Valid | H10: https://github.com/IsepMartimOliveira/desofs2025_wed_ffs_4/blob/main/src/main/java/com/example/psoft_22_23_project/configuration/SecurityConfig.java | I10: SecurityConfig.java proves integrity protection through HTTPS enforcement, CSP headers blocking untrusted scripts, and strict access controls.
B11: 10.3.3 | C11: 1 | D11: 350 | F11: Verify that the application has protection from subdomain takeovers if the application relies upon DNS entries or DNS subdomains, such as expired domain names, out of date DNS pointers or CNAMEs, expired projects at public source code repos, or transient cloud APIs, serverless functions, or storage buckets (autogen-bucket-id.cloud.example.com) or similar. Protections can include ensuring that DNS names used by applications are regularly checked for expiry or change. | G11: Valid | H11: https://github.com/IsepMartimOliveira/desofs2025_wed_ffs_4/blob/main/src/main/resources/application.properties | I11: Application.properties line 83 to 88

Sheet Business Logic
A1: Area | B1: # | C1: ASVS Level | D1: CWE | E1: NIST | F1: Verification Requirement | G1: Valid | H1: Source Code Reference | I1: Comment | J1: Tool Used
A2: Business Logic Security Requirements | B2: 11.1.1 | C2: 1 | D2: 841 | F2: Verify that the application will only process business logic flows for the same user in sequential step order and without skipping steps. | G2: Valid | H2: https://github.com/IsepMartimOliveira/desofs2025_wed_ffs_4/blob/main/src/main/java/com/example/psoft_22_23_project/subscriptionsmanagement/services/SubscriptionsServiceImpl.java | I2: This requirement is fulfilled by enforcing sequential business logic steps — such as plan selection, subscription creation, cancellation, renewal, and plan changes — while ensuring that only the authenticated user can perform these actions and that each step validates the current subscription state.
B3: 11.1.2 | C3: 1 | D3: 799 | F3: Verify that the application will only process business logic flows with all steps being processed in realistic human time, i.e. transactions are not submitted too quickly. | G3: Valid | H3: https://github.com/IsepMartimOliveira/desofs2025_wed_ffs_4/blob/60685731027efced577ee73517a2d84a07e1e639/src/main/java/com/example/psoft_22_23_project/api/AuthApi.java#L63 | I3: Between line 63 to 148. The login flow implements both IP-based and user-based login throttling. On repeated failed attempts, accounts or IPs are temporarily blocked. This mechanism ensures login cannot be automated or abused at speeds beyond realistic human interaction. While login is a single-step action, similar protections would be extended to multi-step flows as applicable elsewhere in the application.
B4: 11.1.3 | C4: 1 | D4: 770 | F4: Verify the application has appropriate limits for specific business actions or transactions which are correctly enforced on a per user basis. | G4: Valid | H4: https://github.com/IsepMartimOliveira/desofs2025_wed_ffs_4/blob/60685731027efced577ee73517a2d84a07e1e639/src/main/java/com/example/psoft_22_23_project/api/AuthApi.java#L63 | I4: Between line 63 to 148.
B5: 11.1.4 | C5: 1 | D5: 770 | F5: Verify that the application has anti-automation controls to protect against excessive calls such as mass data exfiltration, business logic requests, file uploads or denial of service attacks. | G5: Valid | H5: https://github.com/IsepMartimOliveira/desofs2025_wed_ffs_4/blob/60685731027efced577ee73517a2d84a07e1e639/src/main/java/com/example/psoft_22_23_project/api/AuthApi.java#L63 | I5: Between line 63 to 148.
B6: 11.1.5 | C6: 1 | D6: 841 | F6: Verify the application has business logic limits or validation to protect against likely business risks or threats, identified using threat modeling or similar methodologies. | G6: Valid | H6: https://github.com/IsepMartimOliveira/desofs2025_wed_ffs_4/blob/60685731027efced577ee73517a2d84a07e1e639/src/main/java/com/example/psoft_22_23_project/api/AuthApi.java#L63 | I6: Between line 63 to 148.
B7: 11.1.6 | C7: 2 | D7: 367 | F7: Verify that the application does not suffer from "Time Of Check to Time Of Use" (TOCTOU) issues or other race conditions for sensitive operations. | G7: Valid | H7: https://github.com/IsepMartimOliveira/desofs2025_wed_ffs_4/blob/60685731027efced577ee73517a2d84a07e1e639/src/main/java/com/example/psoft_22_23_project/devicemanagement/services/DeviceServiceImpl.java#L111 | I7: In the line 111. The application uses Spring's @Transactional annotation to ensure that sensitive operations (e.g., financial transactions, record updates) are performed atomically. Business logic validations and data modifications occur in a single transaction, preventing TOCTOU issues.
B8: 11.1.7 | C8: 2 | D8: 754 | F8: Verify that the application monitors for unusual events or activity from a business logic perspective. For example, attempts to perform actions out of order or actions which a normal user would never attempt. ([C9](https://owasp.org/www-project-proactive-controls/#div-numbering)) | G8: Not Applicable
B9: 11.1.8 | C9: 2 | D9: 390 | F9: Verify that the application has configurable alerting when automated attacks or unusual activity is detected. | G9: Not Applicable

Sheet Files and Resources
A1: Area | B1: # | C1: ASVS Level | D1: CWE | E1: NIST | F1: Verification Requirement | G1: Valid | H1: Source Code Reference | I1: Comment | J1: Tool Used
A2: File Upload | B2: 12.1.1 | C2: 1 | D2: 400 | F2: Verify that the application will not accept large files that could fill up storage or cause a denial of service. | G2: Valid | H2: https://github.com/IsepMartimOliveira/desofs2025_wed_ffs_4/blob/main/src/main/resources/application.properties | I2: Upload size limits are configured in application.properties to prevent large file uploads and mitigate DoS risks
B3: 12.1.2 | C3: 2 | D3: 409 | F3: Verify that the application checks compressed files (e.g. zip, gz, docx, odt) against maximum allowed uncompressed size and against maximum number of files before uncompressing the file. | G3: Not Applicable | H3: https://github.com/IsepMartimOliveira/desofs2025_wed_ffs_4/blob/main/src/main/java/com/example/psoft_22_23_project/filestoragemanagement/sanitize/AllowedImage.java | I3: Application does not support/allow compressed files
B4: 12.1.3 | C4: 2 | D4: 770 | F4: Verify that a file size quota and maximum number of files per user is enforced to ensure that a single user cannot fill up the storage with too many files, or excessively large files. | G4: Valid | H4: https://github.com/IsepMartimOliveira/desofs2025_wed_ffs_4/blob/main/src/main/resources/application.properties | I4: Lines 53 and 55. A user can only have one image
A5: File Integrity | B5: 12.2.1 | C5: 2 | D5: 434 | F5: Verify that files obtained from untrusted sources are validated to be of expected type based on the file's content. | G5: Valid | H5: https://github.com/IsepMartimOliveira/desofs2025_wed_ffs_4/blob/main/src/main/java/com/example/psoft_22_23_project/filestoragemanagement/sanitize/SanitizeImage.java | I5: Lines 113 to 121
A6: File Execution | B6: 12.3.1 | C6: 1 | D6: 22 | F6: Verify that user-submitted filename metadata is not used directly by system or framework filesystems and that a URL API is used to protect against path traversal. | G6: Valid | H6: https://github.com/IsepMartimOliveira/desofs2025_wed_ffs_4/blob/main/src/main/java/com/example/psoft_22_23_project/filestoragemanagement/sanitize/SanitizeImage.java#L87 | I6: Lines 87 to 111
B7: 12.3.2 | C7: 1 | D7: 73 | F7: Verify that user-submitted filename metadata is validated or ignored to prevent the disclosure, creation, updating or removal of local files (LFI). | G7: Not Applicable
B8: 12.3.3 | C8: 1 | D8: 98 | F8: Verify that user-submitted filename metadata is validated or ignored to prevent the disclosure or execution of remote files via Remote File Inclusion (RFI) or Server-side Request Forgery (SSRF) attacks. | G8: Not Applicable
B9: 12.3.4 | C9: 1 | D9: 641 | F9: Verify that the application protects against Reflective File Download (RFD) by validating or ignoring user-submitted filenames in a JSON, JSONP, or URL parameter, the response Content-Type header should be set to text/plain, and the Content-Disposition header should have a fixed filename. | G9: Not Applicable
B10: 12.3.5 | C10: 1 | D10: 78 | F10: Verify that untrusted file metadata is not used directly with system API or libraries, to protect against OS command injection. | G10: Not Applicable
B11: 12.3.6 | C11: 2 | D11: 829 | F11: Verify that the application does not include and execute functionality from untrusted sources, such as unverified content distribution networks, JavaScript libraries, node npm libraries, or server-side DLLs. | G11: Not Applicable
A12: File Storage | B12: 12.4.1 | C12: 1 | D12: 922 | F12: Verify that files obtained from untrusted sources are stored outside the web root, with limited permissions. | G12: Valid | H12: https://github.com/IsepMartimOliveira/desofs2025_wed_ffs_4/blob/main/src/main/resources/assets/keep-calm-and-love-jpa.png | I12: The files are stored in a specific folder outside the web root
B13: 12.4.2 | C13: 1 | D13: 509 | F13: Verify that files obtained from untrusted sources are scanned by antivirus scanners to prevent upload and serving of known malicious content. | G13: Not Applicable
A14: File Download | B14: 12.5.1 | C14: 1 | D14: 552 | F14: Verify that the web tier is configured to serve only files with specific file extensions to prevent unintentional information and source code leakage. For example, backup files (e.g. .bak), temporary working files (e.g. .swp), compressed files (.zip, .tar.gz, etc) and other extensions commonly used by editors should be blocked unless required. | G14: Not Applicable
B15: 12.5.2 | C15: 1 | D15: 434 | F15: Verify that direct requests to uploaded files will never be executed as HTML/JavaScript content. | G15: Not Applicable
A16: SSRF Protection | B16: 12.6.1 | C16: 1 | D16: 918 | F16: Verify that the web or application server is configured with an allow list of resources or systems to which the server can send requests or load data/files from. | G16: Not Applicable

Sheet API and Web Service
A1: Area | B1: # | C1: ASVS Level | D1: CWE | E1: NIST | F1: Verification Requirement | G1: Valid | H1: Source Code Reference | I1: Comment | J1: Tool Used
A2: Generic Web Service Security | B2: 13.1.1 | C2: 1 | D2: 116 | F2: Verify that all application components use the same encodings and parsers to avoid parsing attacks that exploit different URI or file parsing behavior that could be used in SSRF and RFI attacks. | G2: Valid | H2: https://github.com/IsepMartimOliveira/desofs2025_wed_ffs_4/blob/main/src/main/java/com/example/psoft_22_23_project/configuration/SecurityConfig.java | I2: This configuration ensures consistent encoding and parsing across all components by integrating the EncodingSecurityFilter for SSRF/RFI protection
B3: 13.1.2 | C3: 1 | D3: 419 | F3: [DELETED, DUPLICATE OF 4.3.1] | G3: Not Applicable
B4: 13.1.3 | C4: 1 | D4: 598 | F4: Verify API URLs do not expose sensitive information, such as the API key, session tokens etc. | G4: Valid | H4: https://github.com/IsepMartimOliveira/desofs2025_wed_ffs_4/blob/main/src/main/java/com/example/psoft_22_23_project/plansmanagement/api/PlansController.java | I4: No sensitive information is exposed
B5: 13.1.4 | C5: 2 | D5: 285 | F5: Verify that authorization decisions are made at both the URI, enforced by programmatic or declarative security at the controller or router, and at the resource level, enforced by model-based permissions. | G5: Valid | H5: https://github.com/IsepMartimOliveira/desofs2025_wed_ffs_4/blob/main/src/main/java/com/example/psoft_22_23_project/configuration/SecurityConfig.java | I5: Lines 163 and 157 for example
B6: 13.1.5 | C6: 2 | D6: 434 | F6: Verify that requests containing unexpected or missing content types are rejected with appropriate headers (HTTP response status 406 Unacceptable or 415 Unsupported Media Type). | G6: Not Applicable
A7: RESTful Web Service | B7: 13.2.1 | C7: 1 | D7: 650 | F7: Verify that enabled RESTful HTTP methods are a valid choice for the user or action, such as preventing normal users using DELETE or PUT on protected API or resources. | G7: Valid | H7: https://github.com/IsepMartimOliveira/desofs2025_wed_ffs_4/blob/main/src/main/java/com/example/psoft_22_23_project/configuration/SecurityConfig.java | I7: Lines 163 and 157 for example
B8: 13.2.2 | C8: 1 | D8: 20 | F8: Verify that JSON schema validation is in place and verified before accepting input. | G8: Valid | H8: https://github.com/IsepMartimOliveira/desofs2025_wed_ffs_4/blob/main/src/main/java/com/example/psoft_22_23_project/plansmanagement/api/CreatePlanRequest.java | I8: CreatePlanRequest for example
B9: 13.2.3 | C9: 1 | D9: 352 | F9: Verify that RESTful web services that utilize cookies are protected from Cross-Site Request Forgery via the use of at least one or more of the following: double submit cookie pattern, CSRF nonces, or Origin request header checks. | G9: Not Applicable
B10: 13.2.4 | C10: 2 | D10: 770 | F10: [DELETED, DUPLICATE OF 11.1.4] | G10: Not Applicable
B11: 13.2.5 | C11: 2 | D11: 436 | F11: Verify that REST services explicitly check the incoming Content-Type to be the expected one, such as application/xml or application/json. | G11: Valid | H11: https://github.com/IsepMartimOliveira/desofs2025_wed_ffs_4/blob/main/src/main/java/com/example/psoft_22_23_project/usermanagement/api/UserController.java | I11: Uses @PostMapping, @PatchMapping, @DeleteMapping with explicit 'consumes' parameter.Validates that incoming requests have the expected Content-Type (application/json).Automatically rejects requests with invalid/missing Content-Type with HTTP 415.
B12: 13.2.6 | C12: 2 | D12: 345 | F12: Verify that the message headers and payload are trustworthy and not modified in transit. Requiring strong encryption for transport (TLS only) may be sufficient in many cases as it provides both confidentiality and integrity protection. Per-message digital signatures can provide additional assurance on top of the transport protections for high-security applications but bring with them additional complexity and risks to weigh against the benefits. | G12: Valid | H12: https://github.com/IsepMartimOliveira/desofs2025_wed_ffs_4/blob/main/src/main/resources/application.properties | I12: In application.properties we have "server.ssl.key-store=classpath:keystore.p12"
A13: SOAP Web Service | B13: 13.3.1 | C13: 1 | D13: 20 | F13: Verify that XSD schema validation takes place to ensure a properly formed XML document, followed by validation of each input field before any processing of that data takes place. | G13: Not Applicable
B14: 13.3.2 | C14: 2 | D14: 345 | F14: Verify that the message payload is signed using WS-Security to ensure reliable transport between client and service. | G14: Not Applicable
A15: GraphQL | B15: 13.4.1 | C15: 2 | D15: 770 | F15: Verify that a query allow list or a combination of depth limiting and amount limiting is used to prevent GraphQL or data layer expression Denial of Service (DoS) as a result of expensive, nested queries. For more advanced scenarios, query cost analysis should be used. | G15: Not Applicable
B16: 13.4.2 | C16: 2 | D16: 285 | F16: Verify that GraphQL or other data layer authorization logic should be implemented at the business logic layer instead of the GraphQL layer. | G16: Not Applicable

Sheet Configuration
A1: Area | B1: # | C1: ASVS Level | D1: CWE | E1: NIST | F1: Verification Requirement | G1: Valid | H1: Source Code Reference | I1: Comment | J1: Tool Used
A2: Build and Deploy | B2: 14.1.1 | C2: 2 | F2: Verify that the application build and deployment processes are performed in a secure and repeatable way, such as CI / CD automation, automated configuration management, and automated deployment scripts. | G2: Valid | H2: https://github.com/IsepMartimOliveira/desofs2025_wed_ffs_4/blob/main/.github/workflows/build_and_publish.yaml
B3: 14.1.2 | C3: 2 | D3: 120 | F3: Verify that compiler flags are configured to enable all available buffer overflow protections and warnings, including stack randomization, data execution prevention, and to break the build if an unsafe pointer, memory, format string, integer, or string operations are found. | G3: Not Applicable
B4: 14.1.3 | C4: 2 | D4: 16 | F4: Verify that server configuration is hardened as per the recommendations of the application server and frameworks in use. | G4: Not Applicable
B5: 14.1.4 | C5: 2 | F5: Verify that the application, configuration, and all dependencies can be re-deployed using automated deployment scripts, built from a documented and tested runbook in a reasonable time, or restored from backups in a timely fashion. | G5: Not Applicable
B6: 14.1.5 | C6: 3 | F6: Verify that authorized administrators can verify the integrity of all security-relevant configurations to detect tampering. | G6: Not Applicable
A7: Dependency | B7: 14.2.1 | C7: 1 | D7: 1026 | F7: Verify that all components are up to date, preferably using a dependency checker during build or compile time. ([C2](https://owasp.org/www-project-proactive-controls/#div-numbering)) | G7: Valid | H7: https://github.com/IsepMartimOliveira/desofs2025_wed_ffs_4/blob/main/pom.xml
B8: 14.2.2 | C8: 1 | D8: 1002 | F8: Verify that all unneeded features, documentation, sample applications and configurations are removed. | G8: Valid
B9: 14.2.3 | C9: 1 | D9: 829 | F9: Verify that if application assets, such as JavaScript libraries, CSS stylesheets or web fonts, are hosted externally on a content delivery network (CDN) or external provider, Subresource Integrity (SRI) is used to validate the integrity of the asset. | G9: Not Applicable | I9: Is just a backend API
B10: 14.2.4 | C10: 2 | D10: 829 | F10: Verify that third party components come from pre-defined, trusted and continually maintained repositories. ([C2](https://owasp.org/www-project-proactive-controls/#div-numbering)) | G10: Valid | H10: https://github.com/IsepMartimOliveira/desofs2025_wed_ffs_4/blob/main/pom.xml | I10: The use of maven helps ensure this
B11: 14.2.5 | C11: 2 | F11: Verify that a Software Bill of Materials (SBOM) is maintained of all third party libraries in use. ([C2](https://owasp.org/www-project-proactive-controls/#div-numbering)) | G11: Not Applicable
B12: 14.2.6 | C12: 2 | D12: 265 | F12: Verify that the attack surface is reduced by sandboxing or encapsulating third party libraries to expose only the required behaviour into the application. ([C2](https://owasp.org/www-project-proactive-controls/#div-numbering)) | G12: Not Applicable
A13: Unintended Security Disclosure | B13: 14.3.1 | C13: 1 | D13: 209 | F13: [DELETED, DUPLICATE OF 7.4.1] | G13: Not Applicable
B14: 14.3.2 | C14: 1 | D14: 497 | F14: Verify that web or application server and application framework debug modes are disabled in production to eliminate debug features, developer consoles, and unintended security disclosures. | G14: Valid | H14: https://github.com/IsepMartimOliveira/desofs2025_wed_ffs_4/blob/main/src/main/resources/application.properties | I14: between lines 73 to 79
B15: 14.3.3 | C15: 1 | D15: 200 | F15: Verify that the HTTP headers or any part of the HTTP response do not expose detailed version information of system components. | G15: Valid
A16: HTTP Security Headers | B16: 14.4.1 | C16: 1 | D16: 173 | F16: Verify that every HTTP response contains a Content-Type header. Also specify a safe character set (e.g., UTF-8, ISO-8859-1) if the content types are text/*, /+xml and application/xml. Content must match with the provided Content-Type header. | G16: Valid | H16: https://github.com/IsepMartimOliveira/desofs2025_wed_ffs_4/blob/main/src/main/java/com/example/psoft_22_23_project/devicemanagement/api/DeviceController.java | I16: In the line75
B17: 14.4.2 | C17: 1 | D17: 116 | F17: Verify that all API responses contain Content-Disposition: attachment; filename="api.json" header (or other appropriate filename for the content type). | G17: Valid | H17: https://github.com/IsepMartimOliveira/desofs2025_wed_ffs_4/blob/main/src/main/java/com/example/psoft_22_23_project/devicemanagement/api/DeviceController.java | I17: between line 146 to 149
B18: 14.4.3 | C18: 1 | D18: 1021 | F18: Verify that a Content Security Policy (CSP) response header is in place that helps mitigate impact for XSS attacks like HTML, DOM, JSON, and JavaScript injection vulnerabilities. | G18: Valid | H18: https://github.com/IsepMartimOliveira/desofs2025_wed_ffs_4/blob/main/src/main/java/com/example/psoft_22_23_project/configuration/SecurityConfig.java | I18: between Lines 184-188
B19: 14.4.4 | C19: 1 | D19: 116 | F19: Verify that all responses contain a X-Content-Type-Options: nosniff header. | G19: Valid | H19: https://github.com/IsepMartimOliveira/desofs2025_wed_ffs_4/blob/main/src/main/java/com/example/psoft_22_23_project/configuration/SecurityConfig.java | I19: between Lines 184-188. By default nosniff is enabled
B20: 14.4.5 | C20: 1 | D20: 523 | F20: Verify that a Strict-Transport-Security header is included on all responses and for all subdomains, such as Strict-Transport-Security: max-age=15724800; includeSubdomains. | G20: Valid | H20: https://github.com/IsepMartimOliveira/desofs2025_wed_ffs_4/blob/main/src/main/java/com/example/psoft_22_23_project/configuration/SecurityConfig.java | I20: between line 99 to 100
B21: 14.4.6 | C21: 1 | D21: 116 | F21: Verify that a suitable Referrer-Policy header is included to avoid exposing sensitive information in the URL through the Referer header to untrusted parties. | G21: Valid | H21: https://github.com/IsepMartimOliveira/desofs2025_wed_ffs_4/blob/main/src/main/java/com/example/psoft_22_23_project/configuration/SecurityConfig.java | I21: between line 189 to 190
B22: 14.4.7 | C22: 1 | D22: 1021 | F22: Verify that the content of a web application cannot be embedded in a third-party site by default and that embedding of the exact resources is only allowed where necessary by using suitable Content-Security-Policy: frame-ancestors and X-Frame-Options response headers. | G22: Valid | H22: https://github.com/IsepMartimOliveira/desofs2025_wed_ffs_4/blob/main/src/main/java/com/example/psoft_22_23_project/configuration/SecurityConfig.java | I22: between line 184 to 188
A23: HTTP Request Header Validation | B23: 14.5.1 | C23: 1 | D23: 749 | F23: Verify that the application server only accepts the HTTP methods in use by the application/API, including pre-flight OPTIONS, and logs/alerts on any requests that are not valid for the application context. | G23: Valid | H23: https://github.com/IsepMartimOliveira/desofs2025_wed_ffs_4/blob/main/src/main/java/com/example/psoft_22_23_project/configuration/SecurityConfig.java | I23: between line 238 and 248
B24: 14.5.2 | C24: 1 | D24: 346 | F24: Verify that the supplied Origin header is not used for authentication or access control decisions, as the Origin header can easily be changed by an attacker. | G24: Valid | H24: https://github.com/IsepMartimOliveira/desofs2025_wed_ffs_4/blob/main/src/main/java/com/example/psoft_22_23_project/configuration/SecurityConfig.java | I24: Betweetn Line 220 and 227 .Because the validation is made by token the solution is compliant
B25: 14.5.3 | C25: 1 | D25: 346 | F25: Verify that the Cross-Origin Resource Sharing (CORS) Access-Control-Allow-Origin header uses a strict allow list of trusted domains and subdomains to match against and does not support the "null" origin. | G25: Not Applicable
B26: 14.5.4 | C26: 2 | D26: 306 | F26: Verify that HTTP headers added by a trusted proxy or SSO devices, such as a bearer token, are authenticated by the application. | G26: Valid | H26: https://github.com/IsepMartimOliveira/desofs2025_wed_ffs_4/blob/main/src/main/java/com/example/psoft_22_23_project/configuration/SecurityConfig.java | I26: Between Line 214 to 216
